Workbook

Sheet Payroll Sep 2026
A1: Nexora Technologies Ltd. — Payroll Register, September 2026
A2: CONFIDENTIAL – Finance & HR only. Amounts in USD. Bonus column (blue) is an input.
A4: Employee ID | B4: Full Name | C4: Department | D4: Designation | E4: Employment Type | F4: Annual Salary | G4: Bank Name | H4: Account No. | I4: Basic Salary | J4: HRA | K4: Transport Allow. | L4: Medical Allow. | M4: Bonus | N4: Gross Pay | O4: Income Tax | P4: Provident Fund | Q4: Health Insurance | R4: Total Deductions | S4: Net Pay
A5: NX-001 | B5: Daniel Carter | C5: Executive | D5: Chief Executive Officer | E5: Full-time | F5: 180000 | G5: Harbor Bank | H5: 4400-07700000 | I5: =ROUND(F5/12,2) -> 15000 | J5: =ROUND(I5*Assumptions!$B$6,2) -> 6000 | K5: =Assumptions!$B$7 -> 150 | L5: =Assumptions!$B$8 -> 100 | M5: 0 | N5: =SUM(I5:M5) -> 21250 | O5: =ROUND(N5*INDEX(Assumptions!$B$15:$B$19,MATCH(F5,Assumptions!$A$15:$A$19,1)),2) -> 4250 | P5: =IF(E5="Full-time",ROUND(I5*Assumptions!$B$9,2),0) -> 1200 | Q5: =Assumptions!$B$10 -> 75 | R5: =SUM(O5:Q5) -> 5525 | S5: =N5-R5 -> 15725
A6: NX-002 | B6: Sophia Bennett | C6: Finance | D6: Chief Financial Officer | E6: Full-time | F6: 150000 | G6: Summit Trust | H6: 4407-07713579 | I6: =ROUND(F6/12,2) -> 12500 | J6: =ROUND(I6*Assumptions!$B$6,2) -> 5000 | K6: =Assumptions!$B$7 -> 150 | L6: =Assumptions!$B$8 -> 100 | M6: 5000 | N6: =SUM(I6:M6) -> 22750 | O6: =ROUND(N6*INDEX(Assumptions!$B$15:$B$19,MATCH(F6,Assumptions!$A$15:$A$19,1)),2) -> 4550 | P6: =IF(E6="Full-time",ROUND(I6*Assumptions!$B$9,2),0) -> 1000 | Q6: =Assumptions!$B$10 -> 75 | R6: =SUM(O6:Q6) -> 5625 | S6: =N6-R6 -> 17125
A7: NX-003 | B7: Marcus Reed | C7: Technology | D7: Chief Technology Officer | E7: Full-time | F7: 155000 | G7: Meridian Bank | H7: 4414-07727158 | I7: =ROUND(F7/12,2) -> 12916.67 | J7: =ROUND(I7*Assumptions!$B$6,2) -> 5166.67 | K7: =Assumptions!$B$7 -> 150 | L7: =Assumptions!$B$8 -> 100 | M7: 2500 | N7: =SUM(I7:M7) -> 20833.34 | O7: =ROUND(N7*INDEX(Assumptions!$B$15:$B$19,MATCH(F7,Assumptions!$A$15:$A$19,1)),2) -> 4166.67 | P7: =IF(E7="Full-time",ROUND(I7*Assumptions!$B$9,2),0) -> 1033.33 | Q7: =Assumptions!$B$10 -> 75 | R7: =SUM(O7:Q7) -> 5275 | S7: =N7-R7 -> 15558.34
A8: NX-004 | B8: Olivia Hughes | C8: Human Resources | D8: HR Manager | E8: Full-time | F8: 88000 | G8: Pioneer Savings | H8: 4421-07740737 | I8: =ROUND(F8/12,2) -> 7333.33 | J8: =ROUND(I8*Assumptions!$B$6,2) -> 2933.33 | K8: =Assumptions!$B$7 -> 150 | L8: =Assumptions!$B$8 -> 100 | M8: 0 | N8: =SUM(I8:M8) -> 10516.66 | O8: =ROUND(N8*INDEX(Assumptions!$B$15:$B$19,MATCH(F8,Assumptions!$A$15:$A$19,1)),2) -> 841.33 | P8: =IF(E8="Full-time",ROUND(I8*Assumptions!$B$9,2),0) -> 586.67 | Q8: =Assumptions!$B$10 -> 75 | R8: =SUM(O8:Q8) -> 1503 | S8: =N8-R8 -> 9013.66
A9: NX-005 | B9: Ethan Brooks | C9: Technology | D9: Senior Software Engineer | E9: Full-time | F9: 105000 | G9: Harbor Bank | H9: 4428-07754316 | I9: =ROUND(F9/12,2) -> 8750 | J9: =ROUND(I9*Assumptions!$B$6,2) -> 3500 | K9: =Assumptions!$B$7 -> 150 | L9: =Assumptions!$B$8 -> 100 | M9: 1200 | N9: =SUM(I9:M9) -> 13700 | O9: =ROUND(N9*INDEX(Assumptions!$B$15:$B$19,MATCH(F9,Assumptions!$A$15:$A$19,1)),2) -> 1644 | P9: =IF(E9="Full-time",ROUND(I9*Assumptions!$B$9,2),0) -> 700 | Q9: =Assumptions!$B$10 -> 75 | R9: =SUM(O9:Q9) -> 2419 | S9: =N9-R9 -> 11281
A10: NX-006 | B10: Isabella Foster | C10: Technology | D10: Software Engineer | E10: Full-time | F10: 82000 | G10: Summit Trust | H10: 4435-07767895 | I10: =ROUND(F10/12,2) -> 6833.33 | J10: =ROUND(I10*Assumptions!$B$6,2) -> 2733.33 | K10: =Assumptions!$B$7 -> 150 | L10: =Assumptions!$B$8 -> 100 | M10: 500 | N10: =SUM(I10:M10) -> 10316.66 | O10: =ROUND(N10*INDEX(Assumptions!$B$15:$B$19,MATCH(F10,Assumptions!$A$15:$A$19,1)),2) -> 825.33 | P10: =IF(E10="Full-time",ROUND(I10*Assumptions!$B$9,2),0) -> 546.67 | Q10: =Assumptions!$B$10 -> 75 | R10: =SUM(O10:Q10) -> 1447 | S10: =N10-R10 -> 8869.66
A11: NX-007 | B11: Liam Sanders | C11: Technology | D11: Software Engineer | E11: Full-time | F11: 80000 | G11: Meridian Bank | H11: 4442-07781474 | I11: =ROUND(F11/12,2) -> 6666.67 | J11: =ROUND(I11*Assumptions!$B$6,2) -> 2666.67 | K11: =Assumptions!$B$7 -> 150 | L11: =Assumptions!$B$8 -> 100 | M11: 0 | N11: =SUM(I11:M11) -> 9583.34 | O11: =ROUND(N11*INDEX(Assumptions!$B$15:$B$19,MATCH(F11,Assumptions!$A$15:$A$19,1)),2) -> 766.67 | P11: =IF(E11="Full-time",ROUND(I11*Assumptions!$B$9,2),0) -> 533.33 | Q11: =Assumptions!$B$10 -> 75 | R11: =SUM(O11:Q11) -> 1375 | S11: =N11-R11 -> 8208.34
A12: NX-008 | B12: Ava Mitchell | C12: Technology | D12: QA Engineer | E12: Full-time | F12: 68000 | G12: Pioneer Savings | H12: 4449-07795053 | I12: =ROUND(F12/12,2) -> 5666.67 | J12: =ROUND(I12*Assumptions!$B$6,2) -> 2266.67 | K12: =Assumptions!$B$7 -> 150 | L12: =Assumptions!$B$8 -> 100 | M12: 300 | N12: =SUM(I12:M12) -> 8483.34 | O12: =ROUND(N12*INDEX(Assumptions!$B$15:$B$19,MATCH(F12,Assumptions!$A$15:$A$19,1)),2) -> 678.67 | P12: =IF(E12="Full-time",ROUND(I12*Assumptions!$B$9,2),0) -> 453.33 | Q12: =Assumptions!$B$10 -> 75 | R12: =SUM(O12:Q12) -> 1207 | S12: =N12-R12 -> 7276.34
A13: NX-009 | B13: Noah Parker | C13: Sales | D13: Sales Manager | E13: Full-time | F13: 98000 | G13: Harbor Bank | H13: 4456-07808632 | I13: =ROUND(F13/12,2) -> 8166.67 | J13: =ROUND(I13*Assumptions!$B$6,2) -> 3266.67 | K13: =Assumptions!$B$7 -> 150 | L13: =Assumptions!$B$8 -> 100 | M13: 1500 | N13: =SUM(I13:M13) -> 13183.34 | O13: =ROUND(N13*INDEX(Assumptions!$B$15:$B$19,MATCH(F13,Assumptions!$A$15:$A$19,1)),2) -> 1582 | P13: =IF(E13="Full-time",ROUND(I13*Assumptions!$B$9,2),0) -> 653.33 | Q13: =Assumptions!$B$10 -> 75 | R13: =SUM(O13:Q13) -> 2310.33 | S13: =N13-R13 -> 10873.01
A14: NX-010 | B14: Emma Collins | C14: Sales | D14: Sales Executive | E14: Full-time | F14: 64000 | G14: Summit Trust | H14: 4463-07822211 | I14: =ROUND(F14/12,2) -> 5333.33 | J14: =ROUND(I14*Assumptions!$B$6,2) -> 2133.33 | K14: =Assumptions!$B$7 -> 150 | L14: =Assumptions!$B$8 -> 100 | M14: 800 | N14: =SUM(I14:M14) -> 8516.66 | O14: =ROUND(N14*INDEX(Assumptions!$B$15:$B$19,MATCH(F14,Assumptions!$A$15:$A$19,1)),2) -> 681.33 | P14: =IF(E14="Full-time",ROUND(I14*Assumptions!$B$9,2),0) -> 426.67 | Q14: =Assumptions!$B$10 -> 75 | R14: =SUM(O14:Q14) -> 1183 | S14: =N14-R14 -> 7333.66
A15: NX-011 | B15: James Ward | C15: Sales | D15: Sales Executive | E15: Full-time | F15: 62000 | G15: Meridian Bank | H15: 4470-07835790 | I15: =ROUND(F15/12,2) -> 5166.67 | J15: =ROUND(I15*Assumptions!$B$6,2) -> 2066.67 | K15: =Assumptions!$B$7 -> 150 | L15: =Assumptions!$B$8 -> 100 | M15: 0 | N15: =SUM(I15:M15) -> 7483.34 | O15: =ROUND(N15*INDEX(Assumptions!$B$15:$B$19,MATCH(F15,Assumptions!$A$15:$A$19,1)),2) -> 598.67 | P15: =IF(E15="Full-time",ROUND(I15*Assumptions!$B$9,2),0) -> 413.33 | Q15: =Assumptions!$B$10 -> 75 | R15: =SUM(O15:Q15) -> 1087 | S15: =N15-R15 -> 6396.34
A16: NX-012 | B16: Mia Turner | C16: Marketing | D16: Marketing Manager | E16: Full-time | F16: 90000 | G16: Pioneer Savings | H16: 4477-07849369 | I16: =ROUND(F16/12,2) -> 7500 | J16: =ROUND(I16*Assumptions!$B$6,2) -> 3000 | K16: =Assumptions!$B$7 -> 150 | L16: =Assumptions!$B$8 -> 100 | M16: 1000 | N16: =SUM(I16:M16) -> 11750 | O16: =ROUND(N16*INDEX(Assumptions!$B$15:$B$19,MATCH(F16,Assumptions!$A$15:$A$19,1)),2) -> 1410 | P16: =IF(E16="Full-time",ROUND(I16*Assumptions!$B$9,2),0) -> 600 | Q16: =Assumptions!$B$10 -> 75 | R16: =SUM(O16:Q16) -> 2085 | S16: =N16-R16 -> 9665
... A24: NX-020 | B24: Ella Morgan | C24: Marketing | D24: Content Writer | E24: Contract | F24: 45000 | G24: Pioneer Savings | H24: 4533-07958001 | I24: =ROUND(F24/12,2) -> 3750 | J24: =ROUND(I24*Assumptions!$B$6,2) -> 1500 | K24: =Assumptions!$B$7 -> 150 | L24: =Assumptions!$B$8 -> 100 | M24: 0 | N24: =SUM(I24:M24) -> 5500 | O24: =ROUND(N24*INDEX(Assumptions!$B$15:$B$19,MATCH(F24,Assumptions!$A$15:$A$19,1)),2) -> 275 | P24: =IF(E24="Full-time",ROUND(I24*Assumptions!$B$9,2),0) -> 0 | Q24: =Assumptions!$B$10 -> 75 | R24: =SUM(O24:Q24) -> 350 | S24: =N24-R24 -> 5150
A25: TOTAL | F25: =SUM(F5:F24) -> 1695000 | I25: =SUM(I5:I24) -> 141250 | J25: =SUM(J5:J24) -> 56500 | K25: =SUM(K5:K24) -> 3000 | L25: =SUM(L5:L24) -> 2000 | M25: =SUM(M5:M24) -> 14750 | N25: =SUM(N5:N24) -> 217500 | O25: =SUM(O5:O24) -> 26060.66 | P25: =SUM(P5:P24) -> 10653.33 | ... S25: =SUM(S5:S24) -> 179286.01

Sheet Department Summary
A1: Payroll Cost by Department – September 2026
A3: Department | B3: Employees | C3: Gross Pay | D3: Total Deductions | E3: Net Pay
A4: Executive | B4: =COUNTIF('Payroll Sep 2026'!$C$5:$C$24,A4) -> 1 | C4: =SUMIF('Payroll Sep 2026'!$C$5:$C$24,$A4,'Payroll Sep 2026'!$N$5:$N$24) -> 21250 | D4: =SUMIF('Payroll Sep 2026'!$C$5:$C$24,$A4,'Payroll Sep 2026'!$R$5:$R$24) -> 5525 | E4: =SUMIF('Payroll Sep 2026'!$C$5:$C$24,$A4,'Payroll Sep 2026'!$S$5:$S$24) -> 15725
A5: Finance | B5: =COUNTIF('Payroll Sep 2026'!$C$5:$C$24,A5) -> 3 | C5: =SUMIF('Payroll Sep 2026'!$C$5:$C$24,$A5,'Payroll Sep 2026'!$N$5:$N$24) -> 38316.66 | D5: =SUMIF('Payroll Sep 2026'!$C$5:$C$24,$A5,'Payroll Sep 2026'!$R$5:$R$24) -> 7671.5 | E5: =SUMIF('Payroll Sep 2026'!$C$5:$C$24,$A5,'Payroll Sep 2026'!$S$5:$S$24) -> 30645.16
A6: Human Resources | B6: =COUNTIF('Payroll Sep 2026'!$C$5:$C$24,A6) -> 2 | C6: =SUMIF('Payroll Sep 2026'!$C$5:$C$24,$A6,'Payroll Sep 2026'!$N$5:$N$24) -> 17550 | D6: =SUMIF('Payroll Sep 2026'!$C$5:$C$24,$A6,'Payroll Sep 2026'!$R$5:$R$24) -> 2303 | E6: =SUMIF('Payroll Sep 2026'!$C$5:$C$24,$A6,'Payroll Sep 2026'!$S$5:$S$24) -> 15247
A7: Marketing | B7: =COUNTIF('Payroll Sep 2026'!$C$5:$C$24,A7) -> 3 | C7: =SUMIF('Payroll Sep 2026'!$C$5:$C$24,$A7,'Payroll Sep 2026'!$N$5:$N$24) -> 24666.66 | D7: =SUMIF('Payroll Sep 2026'!$C$5:$C$24,$A7,'Payroll Sep 2026'!$R$5:$R$24) -> 3267.5 | E7: =SUMIF('Payroll Sep 2026'!$C$5:$C$24,$A7,'Payroll Sep 2026'!$S$5:$S$24) -> 21399.16
A8: Operations | B8: =COUNTIF('Payroll Sep 2026'!$C$5:$C$24,A8) -> 2 | C8: =SUMIF('Payroll Sep 2026'!$C$5:$C$24,$A8,'Payroll Sep 2026'!$N$5:$N$24) -> 17300 | D8: =SUMIF('Payroll Sep 2026'!$C$5:$C$24,$A8,'Payroll Sep 2026'!$R$5:$R$24) -> 2752.83 | E8: =SUMIF('Payroll Sep 2026'!$C$5:$C$24,$A8,'Payroll Sep 2026'!$S$5:$S$24) -> 14547.17
A9: Sales | B9: =COUNTIF('Payroll Sep 2026'!$C$5:$C$24,A9) -> 3 | C9: =SUMIF('Payroll Sep 2026'!$C$5:$C$24,$A9,'Payroll Sep 2026'!$N$5:$N$24) -> 29183.34 | D9: =SUMIF('Payroll Sep 2026'!$C$5:$C$24,$A9,'Payroll Sep 2026'!$R$5:$R$24) -> 4580.33 | E9: =SUMIF('Payroll Sep 2026'!$C$5:$C$24,$A9,'Payroll Sep 2026'!$S$5:$S$24) -> 24603.01
A10: Technology | B10: =COUNTIF('Payroll Sep 2026'!$C$5:$C$24,A10) -> 6 | C10: =SUMIF('Payroll Sep 2026'!$C$5:$C$24,$A10,'Payroll Sep 2026'!$N$5:$N$24) -> 69233.34 | D10: =SUMIF('Payroll Sep 2026'!$C$5:$C$24,$A10,'Payroll Sep 2026'!$R$5:$R$24) -> 12113.83 | E10: =SUMIF('Payroll Sep 2026'!$C$5:$C$24,$A10,'Payroll Sep 2026'!$S$5:$S$24) -> 57119.51
A11: Total | B11: =SUM(B4:B10) -> 20 | C11: =SUM(C4:C10) -> 217500 | D11: =SUM(D4:D10) -> 38213.99 | E11: =SUM(E4:E10) -> 179286.01

Sheet Assumptions
A1: Payroll Assumptions & Rates
A2: Blue cells are inputs; change them and the Payroll sheet recalculates. Fictional company data.
A4: Pay Period | B4: September 2026
A5: Pay Date | B5: 30-Sep-2026
A6: HRA (% of Basic) | B6: 0.4
A7: Transport Allowance (monthly) | B7: 150
A8: Medical Allowance (monthly) | B8: 100
A9: Provident Fund – employee (% of Basic, Full-time only) | B9: 0.08
A10: Health Insurance Premium (monthly) | B10: 75
A13: Income Tax Slabs (rate applies to monthly gross, based on annual salary)
A14: Annual Salary From ($) | B14: Tax Rate
A15: 0 | B15: 0.05
A16: 60000 | B16: 0.08
A17: 90000 | B17: 0.12
A18: 120000 | B18: 0.16
A19: 150000 | B19: 0.2
A21: Note: Slabs, allowances and bonus amounts are illustrative assumptions for test data, not real tax rules.
