Workbook

Sheet Leave Balances
A1: Nexora Technologies Ltd. — Leave Balances 2026
A2: Used days count Approved leave only. Pending shows requests awaiting approval. Carry-forward (blue) is from 2025, capped at 5 days per policy. Report date: 05-Oct-2026.
A4: Employee ID | B4: Full Name | C4: Department | D4: Employment Type | E4: Annual Entitlement | F4: Carry Forward (2025) | G4: Annual Used | H4: Annual Balance | I4: Sick Entitlement | J4: Sick Used | K4: Sick Balance | L4: Casual Entitlement | M4: Casual Used | N4: Casual Balance | O4: Total Days Taken | P4: Pending Days
A5: NX-001 | B5: Daniel Carter | C5: Executive | D5: Full-time | E5: =IF(D5="Contract",'Leave Rules'!$B$6*'Leave Rules'!$B$7,'Leave Rules'!$B$5) -> 20 | F5: 2 | G5: =SUMIFS('Leave Log'!$G$5:$G$62,'Leave Log'!$B$5:$B$62,$A5,'Leave Log'!$D$5:$D$62,"Annual Leave",'Leave Log'!$H$5:$H$62,"Approved") -> 10 | H5: =E5+F5-G5 -> 12 | I5: ='Leave Rules'!$B$8 -> 10 | J5: =SUMIFS('Leave Log'!$G$5:$G$62,'Leave Log'!$B$5:$B$62,$A5,'Leave Log'!$D$5:$D$62,"Sick Leave",'Leave Log'!$H$5:$H$62,"Approved") -> 0 | K5: =I5-J5 -> 10 | L5: ='Leave Rules'!$B$9 -> 6 | M5: =SUMIFS('Leave Log'!$G$5:$G$62,'Leave Log'!$B$5:$B$62,$A5,'Leave Log'!$D$5:$D$62,"Casual Leave",'Leave Log'!$H$5:$H$62,"Approved") -> 0 | N5: =L5-M5 -> 6 | O5: =G5+J5+M5 -> 10 | P5: =SUMIFS('Leave Log'!$G$5:$G$62,'Leave Log'!$B$5:$B$62,$A5,'Leave Log'!$H$5:$H$62,"Pending") -> 0
A6: NX-002 | B6: Sophia Bennett | C6: Finance | D6: Full-time | E6: =IF(D6="Contract",'Leave Rules'!$B$6*'Leave Rules'!$B$7,'Leave Rules'!$B$5) -> 20 | F6: 5 | G6: =SUMIFS('Leave Log'!$G$5:$G$62,'Leave Log'!$B$5:$B$62,$A6,'Leave Log'!$D$5:$D$62,"Annual Leave",'Leave Log'!$H$5:$H$62,"Approved") -> 5 | H6: =E6+F6-G6 -> 20 | I6: ='Leave Rules'!$B$8 -> 10 | J6: =SUMIFS('Leave Log'!$G$5:$G$62,'Leave Log'!$B$5:$B$62,$A6,'Leave Log'!$D$5:$D$62,"Sick Leave",'Leave Log'!$H$5:$H$62,"Approved") -> 2 | K6: =I6-J6 -> 8 | L6: ='Leave Rules'!$B$9 -> 6 | M6: =SUMIFS('Leave Log'!$G$5:$G$62,'Leave Log'!$B$5:$B$62,$A6,'Leave Log'!$D$5:$D$62,"Casual Leave",'Leave Log'!$H$5:$H$62,"Approved") -> 1 | N6: =L6-M6 -> 5 | O6: =G6+J6+M6 -> 8 | P6: =SUMIFS('Leave Log'!$G$5:$G$62,'Leave Log'!$B$5:$B$62,$A6,'Leave Log'!$H$5:$H$62,"Pending") -> 0
A7: NX-003 | B7: Marcus Reed | C7: Technology | D7: Full-time | E7: =IF(D7="Contract",'Leave Rules'!$B$6*'Leave Rules'!$B$7,'Leave Rules'!$B$5) -> 20 | F7: 0 | G7: =SUMIFS('Leave Log'!$G$5:$G$62,'Leave Log'!$B$5:$B$62,$A7,'Leave Log'!$D$5:$D$62,"Annual Leave",'Leave Log'!$H$5:$H$62,"Approved") -> 5 | H7: =E7+F7-G7 -> 15 | I7: ='Leave Rules'!$B$8 -> 10 | J7: =SUMIFS('Leave Log'!$G$5:$G$62,'Leave Log'!$B$5:$B$62,$A7,'Leave Log'!$D$5:$D$62,"Sick Leave",'Leave Log'!$H$5:$H$62,"Approved") -> 0 | K7: =I7-J7 -> 10 | L7: ='Leave Rules'!$B$9 -> 6 | M7: =SUMIFS('Leave Log'!$G$5:$G$62,'Leave Log'!$B$5:$B$62,$A7,'Leave Log'!$D$5:$D$62,"Casual Leave",'Leave Log'!$H$5:$H$62,"Approved") -> 1 | N7: =L7-M7 -> 5 | O7: =G7+J7+M7 -> 6 | P7: =SUMIFS('Leave Log'!$G$5:$G$62,'Leave Log'!$B$5:$B$62,$A7,'Leave Log'!$H$5:$H$62,"Pending") -> 0
A8: NX-004 | B8: Olivia Hughes | C8: Human Resources | D8: Full-time | E8: =IF(D8="Contract",'Leave Rules'!$B$6*'Leave Rules'!$B$7,'Leave Rules'!$B$5) -> 20 | F8: 3 | G8: =SUMIFS('Leave Log'!$G$5:$G$62,'Leave Log'!$B$5:$B$62,$A8,'Leave Log'!$D$5:$D$62,"Annual Leave",'Leave Log'!$H$5:$H$62,"Approved") -> 4 | H8: =E8+F8-G8 -> 19 | I8: ='Leave Rules'!$B$8 -> 10 | J8: =SUMIFS('Leave Log'!$G$5:$G$62,'Leave Log'!$B$5:$B$62,$A8,'Leave Log'!$D$5:$D$62,"Sick Leave",'Leave Log'!$H$5:$H$62,"Approved") -> 3 | K8: =I8-J8 -> 7 | L8: ='Leave Rules'!$B$9 -> 6 | M8: =SUMIFS('Leave Log'!$G$5:$G$62,'Leave Log'!$B$5:$B$62,$A8,'Leave Log'!$D$5:$D$62,"Casual Leave",'Leave Log'!$H$5:$H$62,"Approved") -> 0 | N8: =L8-M8 -> 6 | O8: =G8+J8+M8 -> 7 | P8: =SUMIFS('Leave Log'!$G$5:$G$62,'Leave Log'!$B$5:$B$62,$A8,'Leave Log'!$H$5:$H$62,"Pending") -> 4
A9: NX-005 | B9: Ethan Brooks | C9: Technology | D9: Full-time | E9: =IF(D9="Contract",'Leave Rules'!$B$6*'Leave Rules'!$B$7,'Leave Rules'!$B$5) -> 20 | F9: 4 | G9: =SUMIFS('Leave Log'!$G$5:$G$62,'Leave Log'!$B$5:$B$62,$A9,'Leave Log'!$D$5:$D$62,"Annual Leave",'Leave Log'!$H$5:$H$62,"Approved") -> 10 | H9: =E9+F9-G9 -> 14 | I9: ='Leave Rules'!$B$8 -> 10 | J9: =SUMIFS('Leave Log'!$G$5:$G$62,'Leave Log'!$B$5:$B$62,$A9,'Leave Log'!$D$5:$D$62,"Sick Leave",'Leave Log'!$H$5:$H$62,"Approved") -> 1 | K9: =I9-J9 -> 9 | L9: ='Leave Rules'!$B$9 -> 6 | M9: =SUMIFS('Leave Log'!$G$5:$G$62,'Leave Log'!$B$5:$B$62,$A9,'Leave Log'!$D$5:$D$62,"Casual Leave",'Leave Log'!$H$5:$H$62,"Approved") -> 0 | N9: =L9-M9 -> 6 | O9: =G9+J9+M9 -> 11 | P9: =SUMIFS('Leave Log'!$G$5:$G$62,'Leave Log'!$B$5:$B$62,$A9,'Leave Log'!$H$5:$H$62,"Pending") -> 0
A10: NX-006 | B10: Isabella Foster | C10: Technology | D10: Full-time | E10: =IF(D10="Contract",'Leave Rules'!$B$6*'Leave Rules'!$B$7,'Leave Rules'!$B$5) -> 20 | F10: 1 | G10: =SUMIFS('Leave Log'!$G$5:$G$62,'Leave Log'!$B$5:$B$62,$A10,'Leave Log'!$D$5:$D$62,"Annual Leave",'Leave Log'!$H$5:$H$62,"Approved") -> 5 | H10: =E10+F10-G10 -> 16 | I10: ='Leave Rules'!$B$8 -> 10 | J10: =SUMIFS('Leave Log'!$G$5:$G$62,'Leave Log'!$B$5:$B$62,$A10,'Leave Log'!$D$5:$D$62,"Sick Leave",'Leave Log'!$H$5:$H$62,"Approved") -> 1 | K10: =I10-J10 -> 9 | L10: ='Leave Rules'!$B$9 -> 6 | M10: =SUMIFS('Leave Log'!$G$5:$G$62,'Leave Log'!$B$5:$B$62,$A10,'Leave Log'!$D$5:$D$62,"Casual Leave",'Leave Log'!$H$5:$H$62,"Approved") -> 2 | N10: =L10-M10 -> 4 | O10: =G10+J10+M10 -> 8 | P10: =SUMIFS('Leave Log'!$G$5:$G$62,'Leave Log'!$B$5:$B$62,$A10,'Leave Log'!$H$5:$H$62,"Pending") -> 0
A11: NX-007 | B11: Liam Sanders | C11: Technology | D11: Full-time | E11: =IF(D11="Contract",'Leave Rules'!$B$6*'Leave Rules'!$B$7,'Leave Rules'!$B$5) -> 20 | F11: 5 | G11: =SUMIFS('Leave Log'!$G$5:$G$62,'Leave Log'!$B$5:$B$62,$A11,'Leave Log'!$D$5:$D$62,"Annual Leave",'Leave Log'!$H$5:$H$62,"Approved") -> 5 | H11: =E11+F11-G11 -> 20 | I11: ='Leave Rules'!$B$8 -> 10 | J11: =SUMIFS('Leave Log'!$G$5:$G$62,'Leave Log'!$B$5:$B$62,$A11,'Leave Log'!$D$5:$D$62,"Sick Leave",'Leave Log'!$H$5:$H$62,"Approved") -> 3 | K11: =I11-J11 -> 7 | L11: ='Leave Rules'!$B$9 -> 6 | M11: =SUMIFS('Leave Log'!$G$5:$G$62,'Leave Log'!$B$5:$B$62,$A11,'Leave Log'!$D$5:$D$62,"Casual Leave",'Leave Log'!$H$5:$H$62,"Approved") -> 0 | N11: =L11-M11 -> 6 | O11: =G11+J11+M11 -> 8 | P11: =SUMIFS('Leave Log'!$G$5:$G$62,'Leave Log'!$B$5:$B$62,$A11,'Leave Log'!$H$5:$H$62,"Pending") -> 0
A12: NX-008 | B12: Ava Mitchell | C12: Technology | D12: Full-time | E12: =IF(D12="Contract",'Leave Rules'!$B$6*'Leave Rules'!$B$7,'Leave Rules'!$B$5) -> 20 | F12: 2 | G12: =SUMIFS('Leave Log'!$G$5:$G$62,'Leave Log'!$B$5:$B$62,$A12,'Leave Log'!$D$5:$D$62,"Annual Leave",'Leave Log'!$H$5:$H$62,"Approved") -> 5 | H12: =E12+F12-G12 -> 17 | I12: ='Leave Rules'!$B$8 -> 10 | J12: =SUMIFS('Leave Log'!$G$5:$G$62,'Leave Log'!$B$5:$B$62,$A12,'Leave Log'!$D$5:$D$62,"Sick Leave",'Leave Log'!$H$5:$H$62,"Approved") -> 2 | K12: =I12-J12 -> 8 | L12: ='Leave Rules'!$B$9 -> 6 | M12: =SUMIFS('Leave Log'!$G$5:$G$62,'Leave Log'!$B$5:$B$62,$A12,'Leave Log'!$D$5:$D$62,"Casual Leave",'Leave Log'!$H$5:$H$62,"Approved") -> 1 | N12: =L12-M12 -> 5 | O12: =G12+J12+M12 -> 8 | P12: =SUMIFS('Leave Log'!$G$5:$G$62,'Leave Log'!$B$5:$B$62,$A12,'Leave Log'!$H$5:$H$62,"Pending") -> 0
A13: NX-009 | B13: Noah Parker | C13: Sales | D13: Full-time | E13: =IF(D13="Contract",'Leave Rules'!$B$6*'Leave Rules'!$B$7,'Leave Rules'!$B$5) -> 20 | F13: 0 | G13: =SUMIFS('Leave Log'!$G$5:$G$62,'Leave Log'!$B$5:$B$62,$A13,'Leave Log'!$D$5:$D$62,"Annual Leave",'Leave Log'!$H$5:$H$62,"Approved") -> 5 | H13: =E13+F13-G13 -> 15 | I13: ='Leave Rules'!$B$8 -> 10 | J13: =SUMIFS('Leave Log'!$G$5:$G$62,'Leave Log'!$B$5:$B$62,$A13,'Leave Log'!$D$5:$D$62,"Sick Leave",'Leave Log'!$H$5:$H$62,"Approved") -> 3 | K13: =I13-J13 -> 7 | L13: ='Leave Rules'!$B$9 -> 6 | M13: =SUMIFS('Leave Log'!$G$5:$G$62,'Leave Log'!$B$5:$B$62,$A13,'Leave Log'!$D$5:$D$62,"Casual Leave",'Leave Log'!$H$5:$H$62,"Approved") -> 1 | N13: =L13-M13 -> 5 | O13: =G13+J13+M13 -> 9 | P13: =SUMIFS('Leave Log'!$G$5:$G$62,'Leave Log'!$B$5:$B$62,$A13,'Leave Log'!$H$5:$H$62,"Pending") -> 0
A14: NX-010 | B14: Emma Collins | C14: Sales | D14: Full-time | E14: =IF(D14="Contract",'Leave Rules'!$B$6*'Leave Rules'!$B$7,'Leave Rules'!$B$5) -> 20 | F14: 3 | G14: =SUMIFS('Leave Log'!$G$5:$G$62,'Leave Log'!$B$5:$B$62,$A14,'Leave Log'!$D$5:$D$62,"Annual Leave",'Leave Log'!$H$5:$H$62,"Approved") -> 10 | H14: =E14+F14-G14 -> 13 | I14: ='Leave Rules'!$B$8 -> 10 | J14: =SUMIFS('Leave Log'!$G$5:$G$62,'Leave Log'!$B$5:$B$62,$A14,'Leave Log'!$D$5:$D$62,"Sick Leave",'Leave Log'!$H$5:$H$62,"Approved") -> 0 | K14: =I14-J14 -> 10 | L14: ='Leave Rules'!$B$9 -> 6 | M14: =SUMIFS('Leave Log'!$G$5:$G$62,'Leave Log'!$B$5:$B$62,$A14,'Leave Log'!$D$5:$D$62,"Casual Leave",'Leave Log'!$H$5:$H$62,"Approved") -> 1 | N14: =L14-M14 -> 5 | O14: =G14+J14+M14 -> 11 | P14: =SUMIFS('Leave Log'!$G$5:$G$62,'Leave Log'!$B$5:$B$62,$A14,'Leave Log'!$H$5:$H$62,"Pending") -> 0
A15: NX-011 | B15: James Ward | C15: Sales | D15: Full-time | E15: =IF(D15="Contract",'Leave Rules'!$B$6*'Leave Rules'!$B$7,'Leave Rules'!$B$5) -> 20 | F15: 1 | G15: =SUMIFS('Leave Log'!$G$5:$G$62,'Leave Log'!$B$5:$B$62,$A15,'Leave Log'!$D$5:$D$62,"Annual Leave",'Leave Log'!$H$5:$H$62,"Approved") -> 5 | H15: =E15+F15-G15 -> 16 | I15: ='Leave Rules'!$B$8 -> 10 | J15: =SUMIFS('Leave Log'!$G$5:$G$62,'Leave Log'!$B$5:$B$62,$A15,'Leave Log'!$D$5:$D$62,"Sick Leave",'Leave Log'!$H$5:$H$62,"Approved") -> 2 | K15: =I15-J15 -> 8 | L15: ='Leave Rules'!$B$9 -> 6 | M15: =SUMIFS('Leave Log'!$G$5:$G$62,'Leave Log'!$B$5:$B$62,$A15,'Leave Log'!$D$5:$D$62,"Casual Leave",'Leave Log'!$H$5:$H$62,"Approved") -> 0 | N15: =L15-M15 -> 6 | O15: =G15+J15+M15 -> 7 | P15: =SUMIFS('Leave Log'!$G$5:$G$62,'Leave Log'!$B$5:$B$62,$A15,'Leave Log'!$H$5:$H$62,"Pending") -> 1
A16: NX-012 | B16: Mia Turner | C16: Marketing | D16: Full-time | E16: =IF(D16="Contract",'Leave Rules'!$B$6*'Leave Rules'!$B$7,'Leave Rules'!$B$5) -> 20 | F16: 4 | G16: =SUMIFS('Leave Log'!$G$5:$G$62,'Leave Log'!$B$5:$B$62,$A16,'Leave Log'!$D$5:$D$62,"Annual Leave",'Leave Log'!$H$5:$H$62,"Approved") -> 5 | H16: =E16+F16-G16 -> 19 | I16: ='Leave Rules'!$B$8 -> 10 | J16: =SUMIFS('Leave Log'!$G$5:$G$62,'Leave Log'!$B$5:$B$62,$A16,'Leave Log'!$D$5:$D$62,"Sick Leave",'Leave Log'!$H$5:$H$62,"Approved") -> 2 | K16: =I16-J16 -> 8 | L16: ='Leave Rules'!$B$9 -> 6 | M16: =SUMIFS('Leave Log'!$G$5:$G$62,'Leave Log'!$B$5:$B$62,$A16,'Leave Log'!$D$5:$D$62,"Casual Leave",'Leave Log'!$H$5:$H$62,"Approved") -> 1 | N16: =L16-M16 -> 5 | O16: =G16+J16+M16 -> 8 | P16: =SUMIFS('Leave Log'!$G$5:$G$62,'Leave Log'!$B$5:$B$62,$A16,'Leave Log'!$H$5:$H$62,"Pending") -> 0
... A24: NX-020 | B24: Ella Morgan | C24: Marketing | D24: Contract | E24: =IF(D24="Contract",'Leave Rules'!$B$6*'Leave Rules'!$B$7,'Leave Rules'!$B$5) -> 18 | F24: 0 | G24: =SUMIFS('Leave Log'!$G$5:$G$62,'Leave Log'!$B$5:$B$62,$A24,'Leave Log'!$D$5:$D$62,"Annual Leave",'Leave Log'!$H$5:$H$62,"Approved") -> 3 | H24: =E24+F24-G24 -> 15 | I24: ='Leave Rules'!$B$8 -> 10 | J24: =SUMIFS('Leave Log'!$G$5:$G$62,'Leave Log'!$B$5:$B$62,$A24,'Leave Log'!$D$5:$D$62,"Sick Leave",'Leave Log'!$H$5:$H$62,"Approved") -> 1 | K24: =I24-J24 -> 9 | L24: ='Leave Rules'!$B$9 -> 6 | M24: =SUMIFS('Leave Log'!$G$5:$G$62,'Leave Log'!$B$5:$B$62,$A24,'Leave Log'!$D$5:$D$62,"Casual Leave",'Leave Log'!$H$5:$H$62,"Approved") -> 1 | N24: =L24-M24 -> 5 | O24: =G24+J24+M24 -> 5 | P24: =SUMIFS('Leave Log'!$G$5:$G$62,'Leave Log'!$B$5:$B$62,$A24,'Leave Log'!$H$5:$H$62,"Pending") -> 0
A25: TOTAL | E25: =SUM(E5:E24) -> 396 | F25: =SUM(F5:F24) -> 41 | G25: =SUM(G5:G24) -> 112 | H25: =SUM(H5:H24) -> 325 | I25: =SUM(I5:I24) -> 200 | J25: =SUM(J5:J24) -> 29 | K25: =SUM(K5:K24) -> 171 | L25: =SUM(L5:L24) -> 120 | ... P25: =SUM(P5:P24) -> 10

Sheet Leave Log
A1: Leave Log – 2026 (January to date)
A2: Working Days is a formula (excludes weekends and company holidays). Names are looked up from the Leave Balances sheet. Report date: 05-Oct-2026.
A4: Leave ID | B4: Employee ID | C4: Employee Name | D4: Leave Type | E4: Start Date | F4: End Date | G4: Working Days | H4: Status | I4: Applied On | J4: Approver | K4: Medical Cert | L4: Reason
A5: LV-2026-001 | B5: NX-011 | C5: =INDEX('Leave Balances'!$B$5:$B$24,MATCH(B5,'Leave Balances'!$A$5:$A$24,0)) -> James Ward | D5: Sick Leave | E5: 46034 | F5: 46035 | G5: =NETWORKDAYS(E5,F5,Holidays!$A$5:$A$9) -> 2 | H5: Approved | I5: 46034 | J5: Noah Parker | K5: No | L5: Fever
A6: LV-2026-002 | B6: NX-016 | C6: =INDEX('Leave Balances'!$B$5:$B$24,MATCH(B6,'Leave Balances'!$A$5:$A$24,0)) -> Amelia Russell | D6: Sick Leave | E6: 46042 | F6: 46042 | G6: =NETWORKDAYS(E6,F6,Holidays!$A$5:$A$9) -> 1 | H6: Approved | I6: 46042 | J6: Olivia Hughes | K6: No | L6: Fever
A7: LV-2026-003 | B7: NX-005 | C7: =INDEX('Leave Balances'!$B$5:$B$24,MATCH(B7,'Leave Balances'!$A$5:$A$24,0)) -> Ethan Brooks | D7: Annual Leave | E7: 46048 | F7: 46052 | G7: =NETWORKDAYS(E7,F7,Holidays!$A$5:$A$9) -> 5 | H7: Approved | I7: 46018 | J7: Marcus Reed | K7: NA | L7: Travel
A8: LV-2026-004 | B8: NX-010 | C8: =INDEX('Leave Balances'!$B$5:$B$24,MATCH(B8,'Leave Balances'!$A$5:$A$24,0)) -> Emma Collins | D8: Annual Leave | E8: 46055 | F8: 46059 | G8: =NETWORKDAYS(E8,F8,Holidays!$A$5:$A$9) -> 5 | H8: Approved | I8: 46025 | J8: Noah Parker | K8: NA | L8: Wedding
A9: LV-2026-005 | B9: NX-015 | C9: =INDEX('Leave Balances'!$B$5:$B$24,MATCH(B9,'Leave Balances'!$A$5:$A$24,0)) -> Lucas Gray | D9: Casual Leave | E9: 46062 | F9: 46062 | G9: =NETWORKDAYS(E9,F9,Holidays!$A$5:$A$9) -> 1 | H9: Approved | I9: 46060 | J9: Sophia Bennett | K9: NA | L9: Exam
A10: LV-2026-006 | B10: NX-002 | C10: =INDEX('Leave Balances'!$B$5:$B$24,MATCH(B10,'Leave Balances'!$A$5:$A$24,0)) -> Sophia Bennett | D10: Sick Leave | E10: 46063 | F10: 46064 | G10: =NETWORKDAYS(E10,F10,Holidays!$A$5:$A$9) -> 2 | H10: Approved | I10: 46063 | J10: Daniel Carter | K10: No | L10: Flu
A11: LV-2026-007 | B11: NX-013 | C11: =INDEX('Leave Balances'!$B$5:$B$24,MATCH(B11,'Leave Balances'!$A$5:$A$24,0)) -> Benjamin Hayes | D11: Sick Leave | E11: 46069 | F11: 46069 | G11: =NETWORKDAYS(E11,F11,Holidays!$A$5:$A$9) -> 1 | H11: Approved | I11: 46069 | J11: Mia Turner | K11: No | L11: Headache
A12: LV-2026-008 | B12: NX-006 | C12: =INDEX('Leave Balances'!$B$5:$B$24,MATCH(B12,'Leave Balances'!$A$5:$A$24,0)) -> Isabella Foster | D12: Casual Leave | E12: 46076 | F12: 46077 | G12: =NETWORKDAYS(E12,F12,Holidays!$A$5:$A$9) -> 2 | H12: Approved | I12: 46072 | J12: Marcus Reed | K12: NA | L12: Moving house
A13: LV-2026-009 | B13: NX-014 | C13: =INDEX('Leave Balances'!$B$5:$B$24,MATCH(B13,'Leave Balances'!$A$5:$A$24,0)) -> Charlotte Price | D13: Sick Leave | E13: 46083 | F13: 46085 | G13: =NETWORKDAYS(E13,F13,Holidays!$A$5:$A$9) -> 3 | H13: Approved | I13: 46083 | J13: Sophia Bennett | K13: Yes | L13: Chest infection
A14: LV-2026-010 | B14: NX-005 | C14: =INDEX('Leave Balances'!$B$5:$B$24,MATCH(B14,'Leave Balances'!$A$5:$A$24,0)) -> Ethan Brooks | D14: Sick Leave | E14: 46090 | F14: 46090 | G14: =NETWORKDAYS(E14,F14,Holidays!$A$5:$A$9) -> 1 | H14: Approved | I14: 46090 | J14: Marcus Reed | K14: No | L14: Migraine
A15: LV-2026-011 | B15: NX-018 | C15: =INDEX('Leave Balances'!$B$5:$B$24,MATCH(B15,'Leave Balances'!$A$5:$A$24,0)) -> Harper Jenkins | D15: Annual Leave | E15: 46090 | F15: 46094 | G15: =NETWORKDAYS(E15,F15,Holidays!$A$5:$A$9) -> 5 | H15: Approved | I15: 46060 | J15: Henry Coleman | K15: NA | L15: Vacation
A16: LV-2026-012 | B16: NX-020 | C16: =INDEX('Leave Balances'!$B$5:$B$24,MATCH(B16,'Leave Balances'!$A$5:$A$24,0)) -> Ella Morgan | D16: Casual Leave | E16: 46093 | F16: 46093 | G16: =NETWORKDAYS(E16,F16,Holidays!$A$5:$A$9) -> 1 | H16: Approved | I16: 46091 | J16: Mia Turner | K16: NA | L16: Personal
... A62: LV-2026-058 | B62: NX-004 | C62: =INDEX('Leave Balances'!$B$5:$B$24,MATCH(B62,'Leave Balances'!$A$5:$A$24,0)) -> Olivia Hughes | D62: Annual Leave | E62: 46377 | F62: 46380 | G62: =NETWORKDAYS(E62,F62,Holidays!$A$5:$A$9) -> 4 | H62: Pending | I62: 46332 | J62: — | K62: NA | L62: Year-end holiday

Sheet Monthly Leave Summary
A1: Approved Leave Days by Month – 2026
A2: Formula-driven from the Leave Log (each request falls within a single month).
C3: 1 | D3: 2 | E3: 3 | F3: 4 | G3: 5 | H3: 6 | I3: 7 | J3: 8 | K3: 9 | L3: 10 | M3: 11 | N3: 12
A4: Employee ID | B4: Full Name | C4: Jan | D4: Feb | E4: Mar | F4: Apr | G4: May | H4: Jun | I4: Jul | J4: Aug | K4: Sep | L4: Oct | M4: Nov | N4: Dec | O4: Total
A5: NX-001 | B5: Daniel Carter | C5: =SUMPRODUCT(('Leave Log'!$B$5:$B$62=$A5)*('Leave Log'!$H$5:$H$62="Approved")*(MONTH('Leave Log'!$E$5:$E$62)=C$3)*'Leave Log'!$G$5:$G$62) -> 0 | D5: =SUMPRODUCT(('Leave Log'!$B$5:$B$62=$A5)*('Leave Log'!$H$5:$H$62="Approved")*(MONTH('Leave Log'!$E$5:$E$62)=D$3)*'Leave Log'!$G$5:$G$62) -> 0 | E5: =SUMPRODUCT(('Leave Log'!$B$5:$B$62=$A5)*('Leave Log'!$H$5:$H$62="Approved")*(MONTH('Leave Log'!$E$5:$E$62)=E$3)*'Leave Log'!$G$5:$G$62) -> 5 | F5: =SUMPRODUCT(('Leave Log'!$B$5:$B$62=$A5)*('Leave Log'!$H$5:$H$62="Approved")*(MONTH('Leave Log'!$E$5:$E$62)=F$3)*'Leave Log'!$G$5:$G$62) -> 0 | G5: =SUMPRODUCT(('Leave Log'!$B$5:$B$62=$A5)*('Leave Log'!$H$5:$H$62="Approved")*(MONTH('Leave Log'!$E$5:$E$62)=G$3)*'Leave Log'!$G$5:$G$62) -> 0 | H5: =SUMPRODUCT(('Leave Log'!$B$5:$B$62=$A5)*('Leave Log'!$H$5:$H$62="Approved")*(MONTH('Leave Log'!$E$5:$E$62)=H$3)*'Leave Log'!$G$5:$G$62) -> 0 | I5: =SUMPRODUCT(('Leave Log'!$B$5:$B$62=$A5)*('Leave Log'!$H$5:$H$62="Approved")*(MONTH('Leave Log'!$E$5:$E$62)=I$3)*'Leave Log'!$G$5:$G$62) -> 0 | J5: =SUMPRODUCT(('Leave Log'!$B$5:$B$62=$A5)*('Leave Log'!$H$5:$H$62="Approved")*(MONTH('Leave Log'!$E$5:$E$62)=J$3)*'Leave Log'!$G$5:$G$62) -> 5 | ... N5: =SUMPRODUCT(('Leave Log'!$B$5:$B$62=$A5)*('Leave Log'!$H$5:$H$62="Approved")*(MONTH('Leave Log'!$E$5:$E$62)=N$3)*'Leave Log'!$G$5:$G$62) -> 0 | O5: =SUM(C5:N5) -> 10
A6: NX-002 | B6: Sophia Bennett | C6: =SUMPRODUCT(('Leave Log'!$B$5:$B$62=$A6)*('Leave Log'!$H$5:$H$62="Approved")*(MONTH('Leave Log'!$E$5:$E$62)=C$3)*'Leave Log'!$G$5:$G$62) -> 0 | D6: =SUMPRODUCT(('Leave Log'!$B$5:$B$62=$A6)*('Leave Log'!$H$5:$H$62="Approved")*(MONTH('Leave Log'!$E$5:$E$62)=D$3)*'Leave Log'!$G$5:$G$62) -> 2 | E6: =SUMPRODUCT(('Leave Log'!$B$5:$B$62=$A6)*('Leave Log'!$H$5:$H$62="Approved")*(MONTH('Leave Log'!$E$5:$E$62)=E$3)*'Leave Log'!$G$5:$G$62) -> 0 | F6: =SUMPRODUCT(('Leave Log'!$B$5:$B$62=$A6)*('Leave Log'!$H$5:$H$62="Approved")*(MONTH('Leave Log'!$E$5:$E$62)=F$3)*'Leave Log'!$G$5:$G$62) -> 0 | G6: =SUMPRODUCT(('Leave Log'!$B$5:$B$62=$A6)*('Leave Log'!$H$5:$H$62="Approved")*(MONTH('Leave Log'!$E$5:$E$62)=G$3)*'Leave Log'!$G$5:$G$62) -> 5 | H6: =SUMPRODUCT(('Leave Log'!$B$5:$B$62=$A6)*('Leave Log'!$H$5:$H$62="Approved")*(MONTH('Leave Log'!$E$5:$E$62)=H$3)*'Leave Log'!$G$5:$G$62) -> 0 | I6: =SUMPRODUCT(('Leave Log'!$B$5:$B$62=$A6)*('Leave Log'!$H$5:$H$62="Approved")*(MONTH('Leave Log'!$E$5:$E$62)=I$3)*'Leave Log'!$G$5:$G$62) -> 0 | J6: =SUMPRODUCT(('Leave Log'!$B$5:$B$62=$A6)*('Leave Log'!$H$5:$H$62="Approved")*(MONTH('Leave Log'!$E$5:$E$62)=J$3)*'Leave Log'!$G$5:$G$62) -> 0 | ... N6: =SUMPRODUCT(('Leave Log'!$B$5:$B$62=$A6)*('Leave Log'!$H$5:$H$62="Approved")*(MONTH('Leave Log'!$E$5:$E$62)=N$3)*'Leave Log'!$G$5:$G$62) -> 0 | O6: =SUM(C6:N6) -> 8
A7: NX-003 | B7: Marcus Reed | C7: =SUMPRODUCT(('Leave Log'!$B$5:$B$62=$A7)*('Leave Log'!$H$5:$H$62="Approved")*(MONTH('Leave Log'!$E$5:$E$62)=C$3)*'Leave Log'!$G$5:$G$62) -> 0 | D7: =SUMPRODUCT(('Leave Log'!$B$5:$B$62=$A7)*('Leave Log'!$H$5:$H$62="Approved")*(MONTH('Leave Log'!$E$5:$E$62)=D$3)*'Leave Log'!$G$5:$G$62) -> 0 | E7: =SUMPRODUCT(('Leave Log'!$B$5:$B$62=$A7)*('Leave Log'!$H$5:$H$62="Approved")*(MONTH('Leave Log'!$E$5:$E$62)=E$3)*'Leave Log'!$G$5:$G$62) -> 0 | F7: =SUMPRODUCT(('Leave Log'!$B$5:$B$62=$A7)*('Leave Log'!$H$5:$H$62="Approved")*(MONTH('Leave Log'!$E$5:$E$62)=F$3)*'Leave Log'!$G$5:$G$62) -> 1 | G7: =SUMPRODUCT(('Leave Log'!$B$5:$B$62=$A7)*('Leave Log'!$H$5:$H$62="Approved")*(MONTH('Leave Log'!$E$5:$E$62)=G$3)*'Leave Log'!$G$5:$G$62) -> 0 | H7: =SUMPRODUCT(('Leave Log'!$B$5:$B$62=$A7)*('Leave Log'!$H$5:$H$62="Approved")*(MONTH('Leave Log'!$E$5:$E$62)=H$3)*'Leave Log'!$G$5:$G$62) -> 0 | I7: =SUMPRODUCT(('Leave Log'!$B$5:$B$62=$A7)*('Leave Log'!$H$5:$H$62="Approved")*(MONTH('Leave Log'!$E$5:$E$62)=I$3)*'Leave Log'!$G$5:$G$62) -> 5 | J7: =SUMPRODUCT(('Leave Log'!$B$5:$B$62=$A7)*('Leave Log'!$H$5:$H$62="Approved")*(MONTH('Leave Log'!$E$5:$E$62)=J$3)*'Leave Log'!$G$5:$G$62) -> 0 | ... N7: =SUMPRODUCT(('Leave Log'!$B$5:$B$62=$A7)*('Leave Log'!$H$5:$H$62="Approved")*(MONTH('Leave Log'!$E$5:$E$62)=N$3)*'Leave Log'!$G$5:$G$62) -> 0 | O7: =SUM(C7:N7) -> 6
A8: NX-004 | B8: Olivia Hughes | C8: =SUMPRODUCT(('Leave Log'!$B$5:$B$62=$A8)*('Leave Log'!$H$5:$H$62="Approved")*(MONTH('Leave Log'!$E$5:$E$62)=C$3)*'Leave Log'!$G$5:$G$62) -> 0 | D8: =SUMPRODUCT(('Leave Log'!$B$5:$B$62=$A8)*('Leave Log'!$H$5:$H$62="Approved")*(MONTH('Leave Log'!$E$5:$E$62)=D$3)*'Leave Log'!$G$5:$G$62) -> 0 | E8: =SUMPRODUCT(('Leave Log'!$B$5:$B$62=$A8)*('Leave Log'!$H$5:$H$62="Approved")*(MONTH('Leave Log'!$E$5:$E$62)=E$3)*'Leave Log'!$G$5:$G$62) -> 0 | F8: =SUMPRODUCT(('Leave Log'!$B$5:$B$62=$A8)*('Leave Log'!$H$5:$H$62="Approved")*(MONTH('Leave Log'!$E$5:$E$62)=F$3)*'Leave Log'!$G$5:$G$62) -> 4 | G8: =SUMPRODUCT(('Leave Log'!$B$5:$B$62=$A8)*('Leave Log'!$H$5:$H$62="Approved")*(MONTH('Leave Log'!$E$5:$E$62)=G$3)*'Leave Log'!$G$5:$G$62) -> 0 | H8: =SUMPRODUCT(('Leave Log'!$B$5:$B$62=$A8)*('Leave Log'!$H$5:$H$62="Approved")*(MONTH('Leave Log'!$E$5:$E$62)=H$3)*'Leave Log'!$G$5:$G$62) -> 3 | I8: =SUMPRODUCT(('Leave Log'!$B$5:$B$62=$A8)*('Leave Log'!$H$5:$H$62="Approved")*(MONTH('Leave Log'!$E$5:$E$62)=I$3)*'Leave Log'!$G$5:$G$62) -> 0 | J8: =SUMPRODUCT(('Leave Log'!$B$5:$B$62=$A8)*('Leave Log'!$H$5:$H$62="Approved")*(MONTH('Leave Log'!$E$5:$E$62)=J$3)*'Leave Log'!$G$5:$G$62) -> 0 | ... N8: =SUMPRODUCT(('Leave Log'!$B$5:$B$62=$A8)*('Leave Log'!$H$5:$H$62="Approved")*(MONTH('Leave Log'!$E$5:$E$62)=N$3)*'Leave Log'!$G$5:$G$62) -> 0 | O8: =SUM(C8:N8) -> 7
A9: NX-005 | B9: Ethan Brooks | C9: =SUMPRODUCT(('Leave Log'!$B$5:$B$62=$A9)*('Leave Log'!$H$5:$H$62="Approved")*(MONTH('Leave Log'!$E$5:$E$62)=C$3)*'Leave Log'!$G$5:$G$62) -> 5 | D9: =SUMPRODUCT(('Leave Log'!$B$5:$B$62=$A9)*('Leave Log'!$H$5:$H$62="Approved")*(MONTH('Leave Log'!$E$5:$E$62)=D$3)*'Leave Log'!$G$5:$G$62) -> 0 | E9: =SUMPRODUCT(('Leave Log'!$B$5:$B$62=$A9)*('Leave Log'!$H$5:$H$62="Approved")*(MONTH('Leave Log'!$E$5:$E$62)=E$3)*'Leave Log'!$G$5:$G$62) -> 1 | F9: =SUMPRODUCT(('Leave Log'!$B$5:$B$62=$A9)*('Leave Log'!$H$5:$H$62="Approved")*(MONTH('Leave Log'!$E$5:$E$62)=F$3)*'Leave Log'!$G$5:$G$62) -> 0 | G9: =SUMPRODUCT(('Leave Log'!$B$5:$B$62=$A9)*('Leave Log'!$H$5:$H$62="Approved")*(MONTH('Leave Log'!$E$5:$E$62)=G$3)*'Leave Log'!$G$5:$G$62) -> 0 | H9: =SUMPRODUCT(('Leave Log'!$B$5:$B$62=$A9)*('Leave Log'!$H$5:$H$62="Approved")*(MONTH('Leave Log'!$E$5:$E$62)=H$3)*'Leave Log'!$G$5:$G$62) -> 0 | I9: =SUMPRODUCT(('Leave Log'!$B$5:$B$62=$A9)*('Leave Log'!$H$5:$H$62="Approved")*(MONTH('Leave Log'!$E$5:$E$62)=I$3)*'Leave Log'!$G$5:$G$62) -> 0 | J9: =SUMPRODUCT(('Leave Log'!$B$5:$B$62=$A9)*('Leave Log'!$H$5:$H$62="Approved")*(MONTH('Leave Log'!$E$5:$E$62)=J$3)*'Leave Log'!$G$5:$G$62) -> 0 | ... N9: =SUMPRODUCT(('Leave Log'!$B$5:$B$62=$A9)*('Leave Log'!$H$5:$H$62="Approved")*(MONTH('Leave Log'!$E$5:$E$62)=N$3)*'Leave Log'!$G$5:$G$62) -> 0 | O9: =SUM(C9:N9) -> 11
A10: NX-006 | B10: Isabella Foster | C10: =SUMPRODUCT(('Leave Log'!$B$5:$B$62=$A10)*('Leave Log'!$H$5:$H$62="Approved")*(MONTH('Leave Log'!$E$5:$E$62)=C$3)*'Leave Log'!$G$5:$G$62) -> 0 | D10: =SUMPRODUCT(('Leave Log'!$B$5:$B$62=$A10)*('Leave Log'!$H$5:$H$62="Approved")*(MONTH('Leave Log'!$E$5:$E$62)=D$3)*'Leave Log'!$G$5:$G$62) -> 2 | E10: =SUMPRODUCT(('Leave Log'!$B$5:$B$62=$A10)*('Leave Log'!$H$5:$H$62="Approved")*(MONTH('Leave Log'!$E$5:$E$62)=E$3)*'Leave Log'!$G$5:$G$62) -> 0 | F10: =SUMPRODUCT(('Leave Log'!$B$5:$B$62=$A10)*('Leave Log'!$H$5:$H$62="Approved")*(MONTH('Leave Log'!$E$5:$E$62)=F$3)*'Leave Log'!$G$5:$G$62) -> 0 | G10: =SUMPRODUCT(('Leave Log'!$B$5:$B$62=$A10)*('Leave Log'!$H$5:$H$62="Approved")*(MONTH('Leave Log'!$E$5:$E$62)=G$3)*'Leave Log'!$G$5:$G$62) -> 0 | H10: =SUMPRODUCT(('Leave Log'!$B$5:$B$62=$A10)*('Leave Log'!$H$5:$H$62="Approved")*(MONTH('Leave Log'!$E$5:$E$62)=H$3)*'Leave Log'!$G$5:$G$62) -> 5 | I10: =SUMPRODUCT(('Leave Log'!$B$5:$B$62=$A10)*('Leave Log'!$H$5:$H$62="Approved")*(MONTH('Leave Log'!$E$5:$E$62)=I$3)*'Leave Log'!$G$5:$G$62) -> 0 | J10: =SUMPRODUCT(('Leave Log'!$B$5:$B$62=$A10)*('Leave Log'!$H$5:$H$62="Approved")*(MONTH('Leave Log'!$E$5:$E$62)=J$3)*'Leave Log'!$G$5:$G$62) -> 1 | ... N10: =SUMPRODUCT(('Leave Log'!$B$5:$B$62=$A10)*('Leave Log'!$H$5:$H$62="Approved")*(MONTH('Leave Log'!$E$5:$E$62)=N$3)*'Leave Log'!$G$5:$G$62) -> 0 | O10: =SUM(C10:N10) -> 8
A11: NX-007 | B11: Liam Sanders | C11: =SUMPRODUCT(('Leave Log'!$B$5:$B$62=$A11)*('Leave Log'!$H$5:$H$62="Approved")*(MONTH('Leave Log'!$E$5:$E$62)=C$3)*'Leave Log'!$G$5:$G$62) -> 0 | D11: =SUMPRODUCT(('Leave Log'!$B$5:$B$62=$A11)*('Leave Log'!$H$5:$H$62="Approved")*(MONTH('Leave Log'!$E$5:$E$62)=D$3)*'Leave Log'!$G$5:$G$62) -> 0 | E11: =SUMPRODUCT(('Leave Log'!$B$5:$B$62=$A11)*('Leave Log'!$H$5:$H$62="Approved")*(MONTH('Leave Log'!$E$5:$E$62)=E$3)*'Leave Log'!$G$5:$G$62) -> 0 | F11: =SUMPRODUCT(('Leave Log'!$B$5:$B$62=$A11)*('Leave Log'!$H$5:$H$62="Approved")*(MONTH('Leave Log'!$E$5:$E$62)=F$3)*'Leave Log'!$G$5:$G$62) -> 0 | G11: =SUMPRODUCT(('Leave Log'!$B$5:$B$62=$A11)*('Leave Log'!$H$5:$H$62="Approved")*(MONTH('Leave Log'!$E$5:$E$62)=G$3)*'Leave Log'!$G$5:$G$62) -> 0 | H11: =SUMPRODUCT(('Leave Log'!$B$5:$B$62=$A11)*('Leave Log'!$H$5:$H$62="Approved")*(MONTH('Leave Log'!$E$5:$E$62)=H$3)*'Leave Log'!$G$5:$G$62) -> 0 | I11: =SUMPRODUCT(('Leave Log'!$B$5:$B$62=$A11)*('Leave Log'!$H$5:$H$62="Approved")*(MONTH('Leave Log'!$E$5:$E$62)=I$3)*'Leave Log'!$G$5:$G$62) -> 5 | J11: =SUMPRODUCT(('Leave Log'!$B$5:$B$62=$A11)*('Leave Log'!$H$5:$H$62="Approved")*(MONTH('Leave Log'!$E$5:$E$62)=J$3)*'Leave Log'!$G$5:$G$62) -> 0 | ... N11: =SUMPRODUCT(('Leave Log'!$B$5:$B$62=$A11)*('Leave Log'!$H$5:$H$62="Approved")*(MONTH('Leave Log'!$E$5:$E$62)=N$3)*'Leave Log'!$G$5:$G$62) -> 0 | O11: =SUM(C11:N11) -> 8
A12: NX-008 | B12: Ava Mitchell | C12: =SUMPRODUCT(('Leave Log'!$B$5:$B$62=$A12)*('Leave Log'!$H$5:$H$62="Approved")*(MONTH('Leave Log'!$E$5:$E$62)=C$3)*'Leave Log'!$G$5:$G$62) -> 0 | D12: =SUMPRODUCT(('Leave Log'!$B$5:$B$62=$A12)*('Leave Log'!$H$5:$H$62="Approved")*(MONTH('Leave Log'!$E$5:$E$62)=D$3)*'Leave Log'!$G$5:$G$62) -> 0 | E12: =SUMPRODUCT(('Leave Log'!$B$5:$B$62=$A12)*('Leave Log'!$H$5:$H$62="Approved")*(MONTH('Leave Log'!$E$5:$E$62)=E$3)*'Leave Log'!$G$5:$G$62) -> 1 | F12: =SUMPRODUCT(('Leave Log'!$B$5:$B$62=$A12)*('Leave Log'!$H$5:$H$62="Approved")*(MONTH('Leave Log'!$E$5:$E$62)=F$3)*'Leave Log'!$G$5:$G$62) -> 0 | G12: =SUMPRODUCT(('Leave Log'!$B$5:$B$62=$A12)*('Leave Log'!$H$5:$H$62="Approved")*(MONTH('Leave Log'!$E$5:$E$62)=G$3)*'Leave Log'!$G$5:$G$62) -> 5 | H12: =SUMPRODUCT(('Leave Log'!$B$5:$B$62=$A12)*('Leave Log'!$H$5:$H$62="Approved")*(MONTH('Leave Log'!$E$5:$E$62)=H$3)*'Leave Log'!$G$5:$G$62) -> 0 | I12: =SUMPRODUCT(('Leave Log'!$B$5:$B$62=$A12)*('Leave Log'!$H$5:$H$62="Approved")*(MONTH('Leave Log'!$E$5:$E$62)=I$3)*'Leave Log'!$G$5:$G$62) -> 0 | J12: =SUMPRODUCT(('Leave Log'!$B$5:$B$62=$A12)*('Leave Log'!$H$5:$H$62="Approved")*(MONTH('Leave Log'!$E$5:$E$62)=J$3)*'Leave Log'!$G$5:$G$62) -> 0 | ... N12: =SUMPRODUCT(('Leave Log'!$B$5:$B$62=$A12)*('Leave Log'!$H$5:$H$62="Approved")*(MONTH('Leave Log'!$E$5:$E$62)=N$3)*'Leave Log'!$G$5:$G$62) -> 0 | O12: =SUM(C12:N12) -> 8
A13: NX-009 | B13: Noah Parker | C13: =SUMPRODUCT(('Leave Log'!$B$5:$B$62=$A13)*('Leave Log'!$H$5:$H$62="Approved")*(MONTH('Leave Log'!$E$5:$E$62)=C$3)*'Leave Log'!$G$5:$G$62) -> 0 | D13: =SUMPRODUCT(('Leave Log'!$B$5:$B$62=$A13)*('Leave Log'!$H$5:$H$62="Approved")*(MONTH('Leave Log'!$E$5:$E$62)=D$3)*'Leave Log'!$G$5:$G$62) -> 0 | E13: =SUMPRODUCT(('Leave Log'!$B$5:$B$62=$A13)*('Leave Log'!$H$5:$H$62="Approved")*(MONTH('Leave Log'!$E$5:$E$62)=E$3)*'Leave Log'!$G$5:$G$62) -> 0 | F13: =SUMPRODUCT(('Leave Log'!$B$5:$B$62=$A13)*('Leave Log'!$H$5:$H$62="Approved")*(MONTH('Leave Log'!$E$5:$E$62)=F$3)*'Leave Log'!$G$5:$G$62) -> 5 | G13: =SUMPRODUCT(('Leave Log'!$B$5:$B$62=$A13)*('Leave Log'!$H$5:$H$62="Approved")*(MONTH('Leave Log'!$E$5:$E$62)=G$3)*'Leave Log'!$G$5:$G$62) -> 0 | H13: =SUMPRODUCT(('Leave Log'!$B$5:$B$62=$A13)*('Leave Log'!$H$5:$H$62="Approved")*(MONTH('Leave Log'!$E$5:$E$62)=H$3)*'Leave Log'!$G$5:$G$62) -> 0 | I13: =SUMPRODUCT(('Leave Log'!$B$5:$B$62=$A13)*('Leave Log'!$H$5:$H$62="Approved")*(MONTH('Leave Log'!$E$5:$E$62)=I$3)*'Leave Log'!$G$5:$G$62) -> 0 | J13: =SUMPRODUCT(('Leave Log'!$B$5:$B$62=$A13)*('Leave Log'!$H$5:$H$62="Approved")*(MONTH('Leave Log'!$E$5:$E$62)=J$3)*'Leave Log'!$G$5:$G$62) -> 3 | ... N13: =SUMPRODUCT(('Leave Log'!$B$5:$B$62=$A13)*('Leave Log'!$H$5:$H$62="Approved")*(MONTH('Leave Log'!$E$5:$E$62)=N$3)*'Leave Log'!$G$5:$G$62) -> 0 | O13: =SUM(C13:N13) -> 9
A14: NX-010 | B14: Emma Collins | C14: =SUMPRODUCT(('Leave Log'!$B$5:$B$62=$A14)*('Leave Log'!$H$5:$H$62="Approved")*(MONTH('Leave Log'!$E$5:$E$62)=C$3)*'Leave Log'!$G$5:$G$62) -> 0 | D14: =SUMPRODUCT(('Leave Log'!$B$5:$B$62=$A14)*('Leave Log'!$H$5:$H$62="Approved")*(MONTH('Leave Log'!$E$5:$E$62)=D$3)*'Leave Log'!$G$5:$G$62) -> 5 | E14: =SUMPRODUCT(('Leave Log'!$B$5:$B$62=$A14)*('Leave Log'!$H$5:$H$62="Approved")*(MONTH('Leave Log'!$E$5:$E$62)=E$3)*'Leave Log'!$G$5:$G$62) -> 0 | F14: =SUMPRODUCT(('Leave Log'!$B$5:$B$62=$A14)*('Leave Log'!$H$5:$H$62="Approved")*(MONTH('Leave Log'!$E$5:$E$62)=F$3)*'Leave Log'!$G$5:$G$62) -> 0 | G14: =SUMPRODUCT(('Leave Log'!$B$5:$B$62=$A14)*('Leave Log'!$H$5:$H$62="Approved")*(MONTH('Leave Log'!$E$5:$E$62)=G$3)*'Leave Log'!$G$5:$G$62) -> 0 | H14: =SUMPRODUCT(('Leave Log'!$B$5:$B$62=$A14)*('Leave Log'!$H$5:$H$62="Approved")*(MONTH('Leave Log'!$E$5:$E$62)=H$3)*'Leave Log'!$G$5:$G$62) -> 1 | I14: =SUMPRODUCT(('Leave Log'!$B$5:$B$62=$A14)*('Leave Log'!$H$5:$H$62="Approved")*(MONTH('Leave Log'!$E$5:$E$62)=I$3)*'Leave Log'!$G$5:$G$62) -> 0 | J14: =SUMPRODUCT(('Leave Log'!$B$5:$B$62=$A14)*('Leave Log'!$H$5:$H$62="Approved")*(MONTH('Leave Log'!$E$5:$E$62)=J$3)*'Leave Log'!$G$5:$G$62) -> 5 | ... N14: =SUMPRODUCT(('Leave Log'!$B$5:$B$62=$A14)*('Leave Log'!$H$5:$H$62="Approved")*(MONTH('Leave Log'!$E$5:$E$62)=N$3)*'Leave Log'!$G$5:$G$62) -> 0 | O14: =SUM(C14:N14) -> 11
A15: NX-011 | B15: James Ward | C15: =SUMPRODUCT(('Leave Log'!$B$5:$B$62=$A15)*('Leave Log'!$H$5:$H$62="Approved")*(MONTH('Leave Log'!$E$5:$E$62)=C$3)*'Leave Log'!$G$5:$G$62) -> 2 | D15: =SUMPRODUCT(('Leave Log'!$B$5:$B$62=$A15)*('Leave Log'!$H$5:$H$62="Approved")*(MONTH('Leave Log'!$E$5:$E$62)=D$3)*'Leave Log'!$G$5:$G$62) -> 0 | E15: =SUMPRODUCT(('Leave Log'!$B$5:$B$62=$A15)*('Leave Log'!$H$5:$H$62="Approved")*(MONTH('Leave Log'!$E$5:$E$62)=E$3)*'Leave Log'!$G$5:$G$62) -> 0 | F15: =SUMPRODUCT(('Leave Log'!$B$5:$B$62=$A15)*('Leave Log'!$H$5:$H$62="Approved")*(MONTH('Leave Log'!$E$5:$E$62)=F$3)*'Leave Log'!$G$5:$G$62) -> 0 | G15: =SUMPRODUCT(('Leave Log'!$B$5:$B$62=$A15)*('Leave Log'!$H$5:$H$62="Approved")*(MONTH('Leave Log'!$E$5:$E$62)=G$3)*'Leave Log'!$G$5:$G$62) -> 0 | H15: =SUMPRODUCT(('Leave Log'!$B$5:$B$62=$A15)*('Leave Log'!$H$5:$H$62="Approved")*(MONTH('Leave Log'!$E$5:$E$62)=H$3)*'Leave Log'!$G$5:$G$62) -> 5 | I15: =SUMPRODUCT(('Leave Log'!$B$5:$B$62=$A15)*('Leave Log'!$H$5:$H$62="Approved")*(MONTH('Leave Log'!$E$5:$E$62)=I$3)*'Leave Log'!$G$5:$G$62) -> 0 | J15: =SUMPRODUCT(('Leave Log'!$B$5:$B$62=$A15)*('Leave Log'!$H$5:$H$62="Approved")*(MONTH('Leave Log'!$E$5:$E$62)=J$3)*'Leave Log'!$G$5:$G$62) -> 0 | ... N15: =SUMPRODUCT(('Leave Log'!$B$5:$B$62=$A15)*('Leave Log'!$H$5:$H$62="Approved")*(MONTH('Leave Log'!$E$5:$E$62)=N$3)*'Leave Log'!$G$5:$G$62) -> 0 | O15: =SUM(C15:N15) -> 7
A16: NX-012 | B16: Mia Turner | C16: =SUMPRODUCT(('Leave Log'!$B$5:$B$62=$A16)*('Leave Log'!$H$5:$H$62="Approved")*(MONTH('Leave Log'!$E$5:$E$62)=C$3)*'Leave Log'!$G$5:$G$62) -> 0 | D16: =SUMPRODUCT(('Leave Log'!$B$5:$B$62=$A16)*('Leave Log'!$H$5:$H$62="Approved")*(MONTH('Leave Log'!$E$5:$E$62)=D$3)*'Leave Log'!$G$5:$G$62) -> 0 | E16: =SUMPRODUCT(('Leave Log'!$B$5:$B$62=$A16)*('Leave Log'!$H$5:$H$62="Approved")*(MONTH('Leave Log'!$E$5:$E$62)=E$3)*'Leave Log'!$G$5:$G$62) -> 5 | F16: =SUMPRODUCT(('Leave Log'!$B$5:$B$62=$A16)*('Leave Log'!$H$5:$H$62="Approved")*(MONTH('Leave Log'!$E$5:$E$62)=F$3)*'Leave Log'!$G$5:$G$62) -> 0 | G16: =SUMPRODUCT(('Leave Log'!$B$5:$B$62=$A16)*('Leave Log'!$H$5:$H$62="Approved")*(MONTH('Leave Log'!$E$5:$E$62)=G$3)*'Leave Log'!$G$5:$G$62) -> 1 | H16: =SUMPRODUCT(('Leave Log'!$B$5:$B$62=$A16)*('Leave Log'!$H$5:$H$62="Approved")*(MONTH('Leave Log'!$E$5:$E$62)=H$3)*'Leave Log'!$G$5:$G$62) -> 0 | I16: =SUMPRODUCT(('Leave Log'!$B$5:$B$62=$A16)*('Leave Log'!$H$5:$H$62="Approved")*(MONTH('Leave Log'!$E$5:$E$62)=I$3)*'Leave Log'!$G$5:$G$62) -> 0 | J16: =SUMPRODUCT(('Leave Log'!$B$5:$B$62=$A16)*('Leave Log'!$H$5:$H$62="Approved")*(MONTH('Leave Log'!$E$5:$E$62)=J$3)*'Leave Log'!$G$5:$G$62) -> 0 | ... N16: =SUMPRODUCT(('Leave Log'!$B$5:$B$62=$A16)*('Leave Log'!$H$5:$H$62="Approved")*(MONTH('Leave Log'!$E$5:$E$62)=N$3)*'Leave Log'!$G$5:$G$62) -> 0 | O16: =SUM(C16:N16) -> 8
... A24: NX-020 | B24: Ella Morgan | C24: =SUMPRODUCT(('Leave Log'!$B$5:$B$62=$A24)*('Leave Log'!$H$5:$H$62="Approved")*(MONTH('Leave Log'!$E$5:$E$62)=C$3)*'Leave Log'!$G$5:$G$62) -> 0 | D24: =SUMPRODUCT(('Leave Log'!$B$5:$B$62=$A24)*('Leave Log'!$H$5:$H$62="Approved")*(MONTH('Leave Log'!$E$5:$E$62)=D$3)*'Leave Log'!$G$5:$G$62) -> 0 | E24: =SUMPRODUCT(('Leave Log'!$B$5:$B$62=$A24)*('Leave Log'!$H$5:$H$62="Approved")*(MONTH('Leave Log'!$E$5:$E$62)=E$3)*'Leave Log'!$G$5:$G$62) -> 1 | F24: =SUMPRODUCT(('Leave Log'!$B$5:$B$62=$A24)*('Leave Log'!$H$5:$H$62="Approved")*(MONTH('Leave Log'!$E$5:$E$62)=F$3)*'Leave Log'!$G$5:$G$62) -> 0 | G24: =SUMPRODUCT(('Leave Log'!$B$5:$B$62=$A24)*('Leave Log'!$H$5:$H$62="Approved")*(MONTH('Leave Log'!$E$5:$E$62)=G$3)*'Leave Log'!$G$5:$G$62) -> 3 | H24: =SUMPRODUCT(('Leave Log'!$B$5:$B$62=$A24)*('Leave Log'!$H$5:$H$62="Approved")*(MONTH('Leave Log'!$E$5:$E$62)=H$3)*'Leave Log'!$G$5:$G$62) -> 0 | I24: =SUMPRODUCT(('Leave Log'!$B$5:$B$62=$A24)*('Leave Log'!$H$5:$H$62="Approved")*(MONTH('Leave Log'!$E$5:$E$62)=I$3)*'Leave Log'!$G$5:$G$62) -> 0 | J24: =SUMPRODUCT(('Leave Log'!$B$5:$B$62=$A24)*('Leave Log'!$H$5:$H$62="Approved")*(MONTH('Leave Log'!$E$5:$E$62)=J$3)*'Leave Log'!$G$5:$G$62) -> 0 | ... N24: =SUMPRODUCT(('Leave Log'!$B$5:$B$62=$A24)*('Leave Log'!$H$5:$H$62="Approved")*(MONTH('Leave Log'!$E$5:$E$62)=N$3)*'Leave Log'!$G$5:$G$62) -> 0 | O24: =SUM(C24:N24) -> 5
A25: TOTAL | C25: =SUM(C5:C24) -> 8 | D25: =SUM(D5:D24) -> 11 | E25: =SUM(E5:E24) -> 21 | F25: =SUM(F5:F24) -> 18 | G25: =SUM(G5:G24) -> 21 | H25: =SUM(H5:H24) -> 17 | I25: =SUM(I5:I24) -> 19 | J25: =SUM(J5:J24) -> 21 | ... O25: =SUM(O5:O24) -> 157

Sheet Attendance Sep 2026
A1: Daily Attendance – September 2026
A2: Codes: P = Present (office), W = Work from home, AL = Annual leave, SL = Sick leave, CL = Casual leave. Weekends greyed. Leave codes come from approved Leave Log entries. Late Marks (blue) is an input.
A4: Employee ID | B4: Full Name | C4: 46266 | D4: 46267 | E4: 46268 | F4: 46269 | G4: 46270 | H4: 46271 | I4: 46272 | J4: 46273 | K4: 46274 | L4: 46275 | M4: 46276 | N4: 46277 | O4: 46278 | P4: 46279 | Q4: 46280 | R4: 46281 | S4: 46282 | T4: 46283 | U4: 46284 | V4: 46285 | W4: 46286 | X4: 46287 | Y4: 46288 | Z4: 46289 | AA4: 46290 | AB4: 46291 | AC4: 46292 | AD4: 46293 | AE4: 46294 | AF4: 46295 | AG4: Present (Office) | AH4: Work From Home | AI4: Leave Days | AJ4: Days Paid | AK4: Working Days | AL4: Late Marks | AM4: Leave Log Check | AN4: Check
C5: =LEFT(TEXT(C4,"ddd"),2) -> Tu | D5: =LEFT(TEXT(D4,"ddd"),2) -> We | E5: =LEFT(TEXT(E4,"ddd"),2) -> Th | F5: =LEFT(TEXT(F4,"ddd"),2) -> Fr | G5: =LEFT(TEXT(G4,"ddd"),2) -> Sa | H5: =LEFT(TEXT(H4,"ddd"),2) -> Su | I5: =LEFT(TEXT(I4,"ddd"),2) -> Mo | J5: =LEFT(TEXT(J4,"ddd"),2) -> Tu | ... AF5: =LEFT(TEXT(AF4,"ddd"),2) -> We
A6: NX-001 | B6: Daniel Carter | C6: P | D6: P | E6: P | F6: P | I6: P | J6: P | K6: P | L6: P | M6: P | P6: P | Q6: P | R6: P | S6: P | T6: P | W6: P | X6: P | Y6: P | Z6: P | AA6: P | AD6: P | AE6: P | AF6: P | AG6: =COUNTIF(C6:AF6,"P") -> 22 | AH6: =COUNTIF(C6:AF6,"W") -> 0 | AI6: =COUNTIF(C6:AF6,"AL")+COUNTIF(C6:AF6,"SL")+COUNTIF(C6:AF6,"CL") -> 0 | AJ6: =AG6+AH6+AI6 -> 22 | AK6: =NETWORKDAYS($C$4,$AF$4,Holidays!$A$5:$A$9) -> 22 | AL6: 0 | AM6: =SUMIFS('Leave Log'!$G$5:$G$62,'Leave Log'!$B$5:$B$62,$A6,'Leave Log'!$H$5:$H$62,"Approved",'Leave Log'!$E$5:$E$62,">="&DATE(2026,9,1),'Leave Log'!$E$5:$E$62,"<="&DATE(2026,9,30)) -> 0 | AN6: =IF(AI6=AM6,"OK","CHECK") -> OK
A7: NX-002 | B7: Sophia Bennett | C7: P | D7: W | E7: P | F7: P | I7: W | J7: P | K7: P | L7: P | M7: W | P7: CL | Q7: P | R7: P | S7: P | T7: P | W7: P | X7: P | Y7: P | Z7: P | AA7: W | AD7: P | AE7: P | AF7: P | AG7: =COUNTIF(C7:AF7,"P") -> 17 | AH7: =COUNTIF(C7:AF7,"W") -> 4 | AI7: =COUNTIF(C7:AF7,"AL")+COUNTIF(C7:AF7,"SL")+COUNTIF(C7:AF7,"CL") -> 1 | AJ7: =AG7+AH7+AI7 -> 22 | AK7: =NETWORKDAYS($C$4,$AF$4,Holidays!$A$5:$A$9) -> 22 | AL7: 1 | AM7: =SUMIFS('Leave Log'!$G$5:$G$62,'Leave Log'!$B$5:$B$62,$A7,'Leave Log'!$H$5:$H$62,"Approved",'Leave Log'!$E$5:$E$62,">="&DATE(2026,9,1),'Leave Log'!$E$5:$E$62,"<="&DATE(2026,9,30)) -> 1 | AN7: =IF(AI7=AM7,"OK","CHECK") -> OK
A8: NX-003 | B8: Marcus Reed | C8: W | D8: P | E8: P | F8: P | I8: P | J8: P | K8: P | L8: P | M8: P | P8: W | Q8: P | R8: P | S8: W | T8: P | W8: W | X8: P | Y8: P | Z8: P | AA8: P | AD8: W | AE8: P | AF8: W | AG8: =COUNTIF(C8:AF8,"P") -> 16 | AH8: =COUNTIF(C8:AF8,"W") -> 6 | AI8: =COUNTIF(C8:AF8,"AL")+COUNTIF(C8:AF8,"SL")+COUNTIF(C8:AF8,"CL") -> 0 | AJ8: =AG8+AH8+AI8 -> 22 | AK8: =NETWORKDAYS($C$4,$AF$4,Holidays!$A$5:$A$9) -> 22 | AL8: 0 | AM8: =SUMIFS('Leave Log'!$G$5:$G$62,'Leave Log'!$B$5:$B$62,$A8,'Leave Log'!$H$5:$H$62,"Approved",'Leave Log'!$E$5:$E$62,">="&DATE(2026,9,1),'Leave Log'!$E$5:$E$62,"<="&DATE(2026,9,30)) -> 0 | AN8: =IF(AI8=AM8,"OK","CHECK") -> OK
A9: NX-004 | B9: Olivia Hughes | C9: W | D9: P | E9: P | F9: P | I9: W | J9: W | K9: P | L9: P | M9: P | P9: P | Q9: P | R9: P | S9: P | T9: P | W9: P | X9: P | Y9: W | Z9: P | AA9: P | AD9: W | AE9: P | AF9: W | AG9: =COUNTIF(C9:AF9,"P") -> 16 | AH9: =COUNTIF(C9:AF9,"W") -> 6 | AI9: =COUNTIF(C9:AF9,"AL")+COUNTIF(C9:AF9,"SL")+COUNTIF(C9:AF9,"CL") -> 0 | AJ9: =AG9+AH9+AI9 -> 22 | AK9: =NETWORKDAYS($C$4,$AF$4,Holidays!$A$5:$A$9) -> 22 | AL9: 0 | AM9: =SUMIFS('Leave Log'!$G$5:$G$62,'Leave Log'!$B$5:$B$62,$A9,'Leave Log'!$H$5:$H$62,"Approved",'Leave Log'!$E$5:$E$62,">="&DATE(2026,9,1),'Leave Log'!$E$5:$E$62,"<="&DATE(2026,9,30)) -> 0 | AN9: =IF(AI9=AM9,"OK","CHECK") -> OK
A10: NX-005 | B10: Ethan Brooks | C10: P | D10: W | E10: P | F10: P | I10: P | J10: P | K10: P | L10: P | M10: P | P10: P | Q10: P | R10: W | S10: P | T10: P | W10: AL | X10: AL | Y10: AL | Z10: AL | AA10: AL | AD10: P | AE10: P | AF10: P | AG10: =COUNTIF(C10:AF10,"P") -> 15 | AH10: =COUNTIF(C10:AF10,"W") -> 2 | AI10: =COUNTIF(C10:AF10,"AL")+COUNTIF(C10:AF10,"SL")+COUNTIF(C10:AF10,"CL") -> 5 | AJ10: =AG10+AH10+AI10 -> 22 | AK10: =NETWORKDAYS($C$4,$AF$4,Holidays!$A$5:$A$9) -> 22 | AL10: 2 | AM10: =SUMIFS('Leave Log'!$G$5:$G$62,'Leave Log'!$B$5:$B$62,$A10,'Leave Log'!$H$5:$H$62,"Approved",'Leave Log'!$E$5:$E$62,">="&DATE(2026,9,1),'Leave Log'!$E$5:$E$62,"<="&DATE(2026,9,30)) -> 5 | AN10: =IF(AI10=AM10,"OK","CHECK") -> OK
A11: NX-006 | B11: Isabella Foster | C11: P | D11: P | E11: P | F11: P | I11: P | J11: P | K11: P | L11: W | M11: P | P11: P | Q11: P | R11: W | S11: W | T11: P | W11: P | X11: P | Y11: W | Z11: P | AA11: W | AD11: W | AE11: P | AF11: P | AG11: =COUNTIF(C11:AF11,"P") -> 16 | AH11: =COUNTIF(C11:AF11,"W") -> 6 | AI11: =COUNTIF(C11:AF11,"AL")+COUNTIF(C11:AF11,"SL")+COUNTIF(C11:AF11,"CL") -> 0 | AJ11: =AG11+AH11+AI11 -> 22 | AK11: =NETWORKDAYS($C$4,$AF$4,Holidays!$A$5:$A$9) -> 22 | AL11: 1 | AM11: =SUMIFS('Leave Log'!$G$5:$G$62,'Leave Log'!$B$5:$B$62,$A11,'Leave Log'!$H$5:$H$62,"Approved",'Leave Log'!$E$5:$E$62,">="&DATE(2026,9,1),'Leave Log'!$E$5:$E$62,"<="&DATE(2026,9,30)) -> 0 | AN11: =IF(AI11=AM11,"OK","CHECK") -> OK
A12: NX-007 | B12: Liam Sanders | C12: W | D12: SL | E12: SL | F12: SL | I12: W | J12: W | K12: W | L12: W | M12: W | P12: W | Q12: W | R12: W | S12: W | T12: W | W12: W | X12: W | Y12: W | Z12: W | AA12: W | AD12: W | AE12: W | AF12: W | AG12: =COUNTIF(C12:AF12,"P") -> 0 | AH12: =COUNTIF(C12:AF12,"W") -> 19 | AI12: =COUNTIF(C12:AF12,"AL")+COUNTIF(C12:AF12,"SL")+COUNTIF(C12:AF12,"CL") -> 3 | AJ12: =AG12+AH12+AI12 -> 22 | AK12: =NETWORKDAYS($C$4,$AF$4,Holidays!$A$5:$A$9) -> 22 | AL12: 0 | AM12: =SUMIFS('Leave Log'!$G$5:$G$62,'Leave Log'!$B$5:$B$62,$A12,'Leave Log'!$H$5:$H$62,"Approved",'Leave Log'!$E$5:$E$62,">="&DATE(2026,9,1),'Leave Log'!$E$5:$E$62,"<="&DATE(2026,9,30)) -> 3 | AN12: =IF(AI12=AM12,"OK","CHECK") -> OK
A13: NX-008 | B13: Ava Mitchell | C13: W | D13: P | E13: P | F13: P | I13: P | J13: P | K13: P | L13: P | M13: W | P13: P | Q13: P | R13: W | S13: W | T13: P | W13: P | X13: P | Y13: P | Z13: P | AA13: W | AD13: P | AE13: P | AF13: P | AG13: =COUNTIF(C13:AF13,"P") -> 17 | AH13: =COUNTIF(C13:AF13,"W") -> 5 | AI13: =COUNTIF(C13:AF13,"AL")+COUNTIF(C13:AF13,"SL")+COUNTIF(C13:AF13,"CL") -> 0 | AJ13: =AG13+AH13+AI13 -> 22 | AK13: =NETWORKDAYS($C$4,$AF$4,Holidays!$A$5:$A$9) -> 22 | AL13: 0 | AM13: =SUMIFS('Leave Log'!$G$5:$G$62,'Leave Log'!$B$5:$B$62,$A13,'Leave Log'!$H$5:$H$62,"Approved",'Leave Log'!$E$5:$E$62,">="&DATE(2026,9,1),'Leave Log'!$E$5:$E$62,"<="&DATE(2026,9,30)) -> 0 | AN13: =IF(AI13=AM13,"OK","CHECK") -> OK
A14: NX-009 | B14: Noah Parker | C14: P | D14: P | E14: P | F14: P | I14: P | J14: W | K14: W | L14: P | M14: P | P14: P | Q14: P | R14: P | S14: W | T14: P | W14: W | X14: P | Y14: P | Z14: P | AA14: W | AD14: CL | AE14: W | AF14: P | AG14: =COUNTIF(C14:AF14,"P") -> 15 | AH14: =COUNTIF(C14:AF14,"W") -> 6 | AI14: =COUNTIF(C14:AF14,"AL")+COUNTIF(C14:AF14,"SL")+COUNTIF(C14:AF14,"CL") -> 1 | AJ14: =AG14+AH14+AI14 -> 22 | AK14: =NETWORKDAYS($C$4,$AF$4,Holidays!$A$5:$A$9) -> 22 | AL14: 3 | AM14: =SUMIFS('Leave Log'!$G$5:$G$62,'Leave Log'!$B$5:$B$62,$A14,'Leave Log'!$H$5:$H$62,"Approved",'Leave Log'!$E$5:$E$62,">="&DATE(2026,9,1),'Leave Log'!$E$5:$E$62,"<="&DATE(2026,9,30)) -> 1 | AN14: =IF(AI14=AM14,"OK","CHECK") -> OK
A15: NX-010 | B15: Emma Collins | C15: P | D15: P | E15: P | F15: W | I15: W | J15: P | K15: P | L15: P | M15: W | P15: P | Q15: P | R15: P | S15: W | T15: P | W15: P | X15: P | Y15: P | Z15: P | AA15: P | AD15: P | AE15: P | AF15: P | AG15: =COUNTIF(C15:AF15,"P") -> 18 | AH15: =COUNTIF(C15:AF15,"W") -> 4 | AI15: =COUNTIF(C15:AF15,"AL")+COUNTIF(C15:AF15,"SL")+COUNTIF(C15:AF15,"CL") -> 0 | AJ15: =AG15+AH15+AI15 -> 22 | AK15: =NETWORKDAYS($C$4,$AF$4,Holidays!$A$5:$A$9) -> 22 | AL15: 1 | AM15: =SUMIFS('Leave Log'!$G$5:$G$62,'Leave Log'!$B$5:$B$62,$A15,'Leave Log'!$H$5:$H$62,"Approved",'Leave Log'!$E$5:$E$62,">="&DATE(2026,9,1),'Leave Log'!$E$5:$E$62,"<="&DATE(2026,9,30)) -> 0 | AN15: =IF(AI15=AM15,"OK","CHECK") -> OK
A16: NX-011 | B16: James Ward | C16: P | D16: P | E16: P | F16: W | I16: P | J16: P | K16: P | L16: W | M16: P | P16: W | Q16: P | R16: P | S16: P | T16: P | W16: P | X16: W | Y16: W | Z16: P | AA16: P | AD16: P | AE16: P | AF16: P | AG16: =COUNTIF(C16:AF16,"P") -> 17 | AH16: =COUNTIF(C16:AF16,"W") -> 5 | AI16: =COUNTIF(C16:AF16,"AL")+COUNTIF(C16:AF16,"SL")+COUNTIF(C16:AF16,"CL") -> 0 | AJ16: =AG16+AH16+AI16 -> 22 | AK16: =NETWORKDAYS($C$4,$AF$4,Holidays!$A$5:$A$9) -> 22 | AL16: 2 | AM16: =SUMIFS('Leave Log'!$G$5:$G$62,'Leave Log'!$B$5:$B$62,$A16,'Leave Log'!$H$5:$H$62,"Approved",'Leave Log'!$E$5:$E$62,">="&DATE(2026,9,1),'Leave Log'!$E$5:$E$62,"<="&DATE(2026,9,30)) -> 0 | AN16: =IF(AI16=AM16,"OK","CHECK") -> OK
A17: NX-012 | B17: Mia Turner | C17: W | D17: P | E17: P | F17: W | I17: P | J17: W | K17: SL | L17: SL | M17: P | P17: P | Q17: P | R17: P | S17: W | T17: P | W17: W | X17: P | Y17: P | Z17: W | AA17: P | AD17: P | AE17: W | AF17: P | AG17: =COUNTIF(C17:AF17,"P") -> 13 | AH17: =COUNTIF(C17:AF17,"W") -> 7 | AI17: =COUNTIF(C17:AF17,"AL")+COUNTIF(C17:AF17,"SL")+COUNTIF(C17:AF17,"CL") -> 2 | AJ17: =AG17+AH17+AI17 -> 22 | AK17: =NETWORKDAYS($C$4,$AF$4,Holidays!$A$5:$A$9) -> 22 | AL17: 0 | AM17: =SUMIFS('Leave Log'!$G$5:$G$62,'Leave Log'!$B$5:$B$62,$A17,'Leave Log'!$H$5:$H$62,"Approved",'Leave Log'!$E$5:$E$62,">="&DATE(2026,9,1),'Leave Log'!$E$5:$E$62,"<="&DATE(2026,9,30)) -> 2 | AN17: =IF(AI17=AM17,"OK","CHECK") -> OK
... A25: NX-020 | B25: Ella Morgan | C25: W | D25: W | E25: W | F25: W | I25: W | J25: W | K25: W | L25: W | M25: W | P25: W | Q25: W | R25: W | S25: W | T25: W | W25: SL | X25: W | Y25: W | Z25: W | AA25: W | AD25: W | AE25: W | AF25: W | AG25: =COUNTIF(C25:AF25,"P") -> 0 | AH25: =COUNTIF(C25:AF25,"W") -> 21 | AI25: =COUNTIF(C25:AF25,"AL")+COUNTIF(C25:AF25,"SL")+COUNTIF(C25:AF25,"CL") -> 1 | AJ25: =AG25+AH25+AI25 -> 22 | AK25: =NETWORKDAYS($C$4,$AF$4,Holidays!$A$5:$A$9) -> 22 | AL25: 0 | AM25: =SUMIFS('Leave Log'!$G$5:$G$62,'Leave Log'!$B$5:$B$62,$A25,'Leave Log'!$H$5:$H$62,"Approved",'Leave Log'!$E$5:$E$62,">="&DATE(2026,9,1),'Leave Log'!$E$5:$E$62,"<="&DATE(2026,9,30)) -> 1 | AN25: =IF(AI25=AM25,"OK","CHECK") -> OK

Sheet Holidays
A1: Company Holiday Calendar 2026
A2: Public holidays are excluded from leave-day counts (NETWORKDAYS). Blue = inputs.
A4: Date | B4: Holiday | C4: Day
A5: 46023 | B5: New Year's Day | C5: =TEXT(A5,"dddd") -> Thursday
A6: 46115 | B6: Good Friday | C6: =TEXT(A6,"dddd") -> Friday
A7: 46143 | B7: Labour Day | C7: =TEXT(A7,"dddd") -> Friday
A8: 46352 | B8: Thanksgiving Day | C8: =TEXT(A8,"dddd") -> Thursday
A9: 46381 | B9: Christmas Day | C9: =TEXT(A9,"dddd") -> Friday

Sheet Leave Rules
A1: Leave Rules (2026) – per Company Policies manual, Section 3
A2: Blue = input. Change a value and balances recalculate. Maternity (90 days) and Paternity (10 days) are not used in 2026 records.
A4: Rule | B4: Value | C4: Notes
A5: Annual Leave – Full-time (days/yr) | B5: 20 | C5: Up to 5 unused days carried forward; rest lapse 31 March.
A6: Annual Leave – Contract (days per completed month) | B6: 1.5 | C6: Pro rata at 1.5 days per completed month.
A7: Contract: completed months counted in 2026 | B7: 12 | C7: Both contract employees joined before 2025, so a full year applies.
A8: Sick Leave (days/yr) | B8: 10 | C8: Medical certificate required for 3+ consecutive days.
A9: Casual Leave (days/yr) | B9: 6 | C9: Max 2 consecutive days; not carried forward.
A10: Standard working days per month (payroll) | B10: 22 | C10: Used for unpaid-leave deduction (1/22 of basic).
