Workbook

Sheet Summary
A1: Nexora Technologies Ltd. — Financial Summary
A2: CONFIDENTIAL – Board of Directors, CEO and CFO only. Amounts in USD. Fictional test data. Blue = hardcoded input, black = formula, green = link to another sheet.
A4: Key metric | B4: FY2024 | C4: FY2025 | D4: 2026 YTD (9M)
A5: Revenue | B5: ='Income Statement'!B10 -> 3950000 | C5: ='Income Statement'!C10 -> 4500000 | D5: ='Income Statement'!G10 -> 3630000
A6: Gross profit | B6: ='Income Statement'!B17 -> 2662300 | C6: ='Income Statement'!C17 -> 3090700 | D6: ='Income Statement'!G17 -> 2531400
A7: Operating profit (EBIT) | B7: ='Income Statement'!B36 -> 199000 | C7: ='Income Statement'!C36 -> 461500 | D7: ='Income Statement'!G36 -> 491900
A8: Net profit | B8: ='Income Statement'!B41 -> 129000 | C8: ='Income Statement'!C41 -> 327000 | D8: ='Income Statement'!G41 -> 354750
A9: Gross margin | B9: ='Income Statement'!B18 -> 0.674 | C9: ='Income Statement'!C18 -> 0.68682222 | D9: ='Income Statement'!G18 -> 0.69735537
A10: Operating margin | B10: ='Income Statement'!B37 -> 0.050379747 | C10: ='Income Statement'!C37 -> 0.10255556 | D10: ='Income Statement'!G37 -> 0.13550964
A11: Net margin | B11: ='Income Statement'!B42 -> 0.032658228 | C11: ='Income Statement'!C42 -> 0.072666667 | D11: ='Income Statement'!G42 -> 0.097727273
A12: Total salary cost (3 salary lines) | B12: ='Income Statement'!B13+'Income Statement'!B21+'Income Statement'!B22 -> 2349000 | C12: ='Income Statement'!C13+'Income Statement'!C21+'Income Statement'!C22 -> 2479500 | D12: ='Income Statement'!G13+'Income Statement'!G21+'Income Statement'!G22 -> 1911900
A13: Salary cost as % of revenue | B13: =B12/B5 -> 0.59468354 | C13: =C12/C5 -> 0.551 | D13: =D12/D5 -> 0.52669421
A14: Revenue per employee (annualised) | B14: =B5/Assumptions!$B$6 -> 197500 | C14: =C5/Assumptions!$B$6 -> 225000 | D14: =D5/9*12/Assumptions!$B$6 -> 242000
A15: Cash balance (period end) | B15: ='Balance Sheet'!B6 -> 1061000 | C15: ='Balance Sheet'!C6 -> 1151000 | D15: ='Balance Sheet'!D6 -> 1350750
A16: Current ratio | B16: ='Balance Sheet'!B9/'Balance Sheet'!B18 -> 3.8769634 | C16: ='Balance Sheet'!C9/'Balance Sheet'!C18 -> 3.88 | D16: ='Balance Sheet'!D9/'Balance Sheet'!D18 -> 3.9706186
A17: Total bank debt | B17: ='Balance Sheet'!B17+'Balance Sheet'!B19 -> 240000 | C17: ='Balance Sheet'!C17+'Balance Sheet'!C19 -> 180000 | D17: ='Balance Sheet'!D17+'Balance Sheet'!D19 -> 135000
A18: Debt-to-equity | B18: =B17/'Balance Sheet'!B25 -> 0.2125775 | C18: =C17/'Balance Sheet'!C25 -> 0.13473054 | D18: =D17/'Balance Sheet'!D25 -> 0.084335468
A19: Days sales outstanding (DSO) | B19: ='Balance Sheet'!B7/B5*365 -> 35.113924 | C19: ='Balance Sheet'!C7/C5*365 -> 36.5 | D19: ='Balance Sheet'!D7/D5*Assumptions!$B$7 -> 39.107438
A21: Model integrity checks
A22: Balance sheet balances (all 3 dates) | B22: =IF(AND('Balance Sheet'!B27=0,'Balance Sheet'!C27=0,'Balance Sheet'!D27=0),"OK","CHECK") -> OK
A23: Cash flow ties to balance sheet | B23: =IF(AND('Cash Flow'!B23=0,'Cash Flow'!C23=0),"OK","CHECK") -> OK
A24: Payroll ties to Payroll Register ($217,500.00 gross) | B24: =IF('Payroll Reconciliation'!C14=0,"OK","CHECK") -> OK
A25: Q3 salary lines tie to September payroll | B25: =IF(AND('Payroll Reconciliation'!E18=0,'Payroll Reconciliation'!E19=0,'Payroll Reconciliation'!E20=0),"OK","CHECK") -> OK

Sheet Income Statement
A1: Income Statement
A2: CONFIDENTIAL – Board of Directors, CEO and CFO only. Amounts in USD. Fictional test data. Blue = hardcoded input, black = formula, green = link to another sheet.
A4: USD | B4: FY2024 | C4: FY2025 | D4: Q1 2026 | E4: Q2 2026 | F4: Q3 2026 | G4: 2026 YTD (9M) | H4: 2026 Annualised | I4: Annualised vs FY2025
A5: REVENUE
A6: Software Development | B6: 2000000 | C6: 2280000 | D6: 580000 | E6: 615000 | F6: 650000 | G6: =SUM(D6:F6) -> 1845000 | H6: =G6/9*12 -> 2460000 | I6: =IF(C6=0,0,H6/C6-1) -> 0.078947368
A7: IT Support & Managed Services | B7: 920000 | C7: 1050000 | D7: 270000 | E7: 285000 | F7: 300000 | G7: =SUM(D7:F7) -> 855000 | H7: =G7/9*12 -> 1140000 | I7: =IF(C7=0,0,H7/C7-1) -> 0.085714286
A8: Digital Marketing Services | B8: 600000 | C8: 690000 | D8: 170000 | E8: 185000 | F8: 200000 | G8: =SUM(D8:F8) -> 555000 | H8: =G8/9*12 -> 740000 | I8: =IF(C8=0,0,H8/C8-1) -> 0.072463768
A9: Consulting | B9: 430000 | C9: 480000 | D9: 120000 | E9: 125000 | F9: 130000 | G9: =SUM(D9:F9) -> 375000 | H9: =G9/9*12 -> 500000 | I9: =IF(C9=0,0,H9/C9-1) -> 0.041666667
A10: Total Revenue | B10: =SUM(B6:B9) -> 3950000 | C10: =SUM(C6:C9) -> 4500000 | D10: =SUM(D6:D9) -> 1140000 | E10: =SUM(E6:E9) -> 1210000 | F10: =SUM(F6:F9) -> 1280000 | G10: =SUM(G6:G9) -> 3630000 | H10: =G10/9*12 -> 4840000 | I10: =IF(C10=0,0,H10/C10-1) -> 0.075555556
A12: COST OF REVENUE
A13: Delivery team salaries (Technology) | B13: 747700 | C13: 789300 | D13: 198400 | E13: 202500 | F13: 207700.02 | G13: =SUM(D13:F13) -> 608600.02 | H13: =G13/9*12 -> 811466.69 | I13: =IF(C13=0,0,H13/C13-1) -> 0.02808399
A14: Cloud hosting & third-party licences | B14: 330000 | C14: 385000 | D14: 95000 | E14: 102000 | F14: 110000 | G14: =SUM(D14:F14) -> 307000 | H14: =G14/9*12 -> 409333.33 | I14: =IF(C14=0,0,H14/C14-1) -> 0.063203463
A15: Subcontractors | B15: 210000 | C15: 235000 | D15: 60000 | E15: 55000 | F15: 68000 | G15: =SUM(D15:F15) -> 183000 | H15: =G15/9*12 -> 244000 | I15: =IF(C15=0,0,H15/C15-1) -> 0.038297872
A16: Total Cost of Revenue | B16: =SUM(B13:B15) -> 1287700 | C16: =SUM(C13:C15) -> 1409300 | D16: =SUM(D13:D15) -> 353400 | E16: =SUM(E13:E15) -> 359500 | F16: =SUM(F13:F15) -> 385700.02 | G16: =SUM(G13:G15) -> 1098600 | H16: =G16/9*12 -> 1464800 | I16: =IF(C16=0,0,H16/C16-1) -> 0.039381272
A17: Gross Profit | B17: =B10-B16 -> 2662300 | C17: =C10-C16 -> 3090700 | D17: =D10-D16 -> 786600 | E17: =E10-E16 -> 850500 | F17: =F10-F16 -> 894299.98 | G17: =G10-G16 -> 2531400 | H17: =G17/9*12 -> 3375200 | I17: =IF(C17=0,0,H17/C17-1) -> 0.092050336
A18: Gross margin % | B18: =IF(B10=0,0,B17/B10) -> 0.674 | C18: =IF(C10=0,0,C17/C10) -> 0.68682222 | D18: =IF(D10=0,0,D17/D10) -> 0.69 | E18: =IF(E10=0,0,E17/E10) -> 0.70289256 | F18: =IF(F10=0,0,F17/F10) -> 0.69867186 | G18: =IF(G10=0,0,G17/G10) -> 0.69735537 | H18: =IF(H10=0,0,H17/H10) -> 0.69735537
A20: OPERATING EXPENSES
A21: Sales & Marketing salaries | B21: 581600 | C21: 613900 | D21: 154300 | E21: 157500 | F21: 161550 | G21: =SUM(D21:F21) -> 473350 | H21: =G21/9*12 -> 631133.33 | I21: =IF(C21=0,0,H21/C21-1) -> 0.02807189
A22: G&A salaries (Executive, Finance, HR, Operations) | B22: 1019700 | C22: 1076300 | D22: 270500 | E22: 276200 | F22: 283249.98 | G22: =SUM(D22:F22) -> 829949.98 | H22: =G22/9*12 -> 1106600 | I22: =IF(C22=0,0,H22/C22-1) -> 0.028151977
A23: Rent & facilities | B23: 290000 | C23: 306000 | D23: 78000 | E23: 78000 | F23: 78000 | G23: =SUM(D23:F23) -> 234000 | H23: =G23/9*12 -> 312000 | I23: =IF(C23=0,0,H23/C23-1) -> 0.019607843
A24: Utilities & internet | B24: 54000 | C24: 58000 | D24: 14500 | E24: 15000 | F24: 15200 | G24: =SUM(D24:F24) -> 44700 | H24: =G24/9*12 -> 59600 | I24: =IF(C24=0,0,H24/C24-1) -> 0.027586207
A25: Software & subscriptions | B25: 78000 | C25: 88000 | D25: 22000 | E25: 23000 | F25: 24500 | G25: =SUM(D25:F25) -> 69500 | H25: =G25/9*12 -> 92666.667 | I25: =IF(C25=0,0,H25/C25-1) -> 0.053030303
A26: Marketing & advertising | B26: 130000 | C26: 150000 | D26: 38000 | E26: 42000 | F26: 45000 | G26: =SUM(D26:F26) -> 125000 | H26: =G26/9*12 -> 166666.67 | I26: =IF(C26=0,0,H26/C26-1) -> 0.11111111
A27: Travel & entertainment | B27: 60000 | C27: 70000 | D27: 16000 | E27: 18500 | F27: 21000 | G27: =SUM(D27:F27) -> 55500 | H27: =G27/9*12 -> 74000 | I27: =IF(C27=0,0,H27/C27-1) -> 0.057142857
A28: Professional fees (legal, audit) | B28: 66000 | C28: 64000 | D28: 20000 | E28: 12000 | F28: 15000 | G28: =SUM(D28:F28) -> 47000 | H28: =G28/9*12 -> 62666.667 | I28: =IF(C28=0,0,H28/C28-1) -> -0.020833333
A29: Group health insurance (employer share) | B29: 34000 | C29: 36000 | D29: 9000 | E29: 9000 | F29: 9000 | G29: =SUM(D29:F29) -> 27000 | H29: =G29/9*12 -> 36000 | I29: =IF(C29=0,0,H29/C29-1) -> 0
A30: Training & development | B30: 8000 | C30: 9500 | D30: 2100 | E30: 3300 | F30: 2600 | G30: =SUM(D30:F30) -> 8000 | H30: =G30/9*12 -> 10666.667 | I30: =IF(C30=0,0,H30/C30-1) -> 0.12280702
A31: Office supplies & pantry | B31: 22000 | C31: 24500 | D31: 6200 | E31: 6500 | F31: 6800 | G31: =SUM(D31:F31) -> 19500 | H31: =G31/9*12 -> 26000 | I31: =IF(C31=0,0,H31/C31-1) -> 0.06122449
A32: Depreciation | B32: 92000 | C32: 100000 | D32: 26000 | E32: 26000 | F32: 27500 | G32: =SUM(D32:F32) -> 79500 | H32: =G32/9*12 -> 106000 | I32: =IF(C32=0,0,H32/C32-1) -> 0.06
A33: Other expenses | B33: 28000 | C33: 33000 | D33: 8000 | E33: 9000 | F33: 9500 | G33: =SUM(D33:F33) -> 26500 | H33: =G33/9*12 -> 35333.333 | I33: =IF(C33=0,0,H33/C33-1) -> 0.070707071
A34: Total Operating Expenses | B34: =SUM(B21:B33) -> 2463300 | C34: =SUM(C21:C33) -> 2629200 | D34: =SUM(D21:D33) -> 664600 | E34: =SUM(E21:E33) -> 676000 | F34: =SUM(F21:F33) -> 698899.98 | G34: =SUM(G21:G33) -> 2039500 | H34: =G34/9*12 -> 2719333.3 | I34: =IF(C34=0,0,H34/C34-1) -> 0.034281647
A36: Operating Profit (EBIT) | B36: =B17-B34 -> 199000 | C36: =C17-C34 -> 461500 | D36: =D17-D34 -> 122000 | E36: =E17-E34 -> 174500 | F36: =F17-F34 -> 195400 | G36: =G17-G34 -> 491900 | H36: =G36/9*12 -> 655866.67 | I36: =IF(C36=0,0,H36/C36-1) -> 0.42116287
A37: Operating margin % | B37: =IF(B10=0,0,B36/B10) -> 0.050379747 | C37: =IF(C10=0,0,C36/C10) -> 0.10255556 | D37: =IF(D10=0,0,D36/D10) -> 0.10701754 | E37: =IF(E10=0,0,E36/E10) -> 0.14421488 | F37: =IF(F10=0,0,F36/F10) -> 0.15265625 | G37: =IF(G10=0,0,G36/G10) -> 0.13550964 | H37: =IF(H10=0,0,H36/H10) -> 0.13550964
A38: Interest expense | B38: 27000 | C38: 25500 | D38: 6500 | E38: 6300 | F38: 6100 | G38: =SUM(D38:F38) -> 18900 | H38: =G38/9*12 -> 25200 | I38: =IF(C38=0,0,H38/C38-1) -> -0.011764706
A39: Profit Before Tax | B39: =B36-B38 -> 172000 | C39: =C36-C38 -> 436000 | D39: =D36-D38 -> 115500 | E39: =E36-E38 -> 168200 | F39: =F36-F38 -> 189300 | G39: =G36-G38 -> 473000 | H39: =G39/9*12 -> 630666.67 | I39: =IF(C39=0,0,H39/C39-1) -> 0.44648318
A40: Income tax | B40: =ROUND(MAX(0,B39)*Assumptions!$B$5,0) -> 43000 | C40: =ROUND(MAX(0,C39)*Assumptions!$B$5,0) -> 109000 | D40: =ROUND(MAX(0,D39)*Assumptions!$B$5,0) -> 28875 | E40: =ROUND(MAX(0,E39)*Assumptions!$B$5,0) -> 42050 | F40: =ROUND(MAX(0,F39)*Assumptions!$B$5,0) -> 47325 | G40: =ROUND(MAX(0,G39)*Assumptions!$B$5,0) -> 118250 | H40: =G40/9*12 -> 157666.67 | I40: =IF(C40=0,0,H40/C40-1) -> 0.44648318
A41: Net Profit | B41: =B39-B40 -> 129000 | C41: =C39-C40 -> 327000 | D41: =D39-D40 -> 86625 | E41: =E39-E40 -> 126150 | F41: =F39-F40 -> 141975 | G41: =G39-G40 -> 354750 | H41: =G41/9*12 -> 473000 | I41: =IF(C41=0,0,H41/C41-1) -> 0.44648318
A42: Net margin % | B42: =IF(B10=0,0,B41/B10) -> 0.032658228 | C42: =IF(C10=0,0,C41/C10) -> 0.072666667 | D42: =IF(D10=0,0,D41/D10) -> 0.075986842 | E42: =IF(E10=0,0,E41/E10) -> 0.1042562 | F42: =IF(F10=0,0,F41/F10) -> 0.11091797 | G42: =IF(G10=0,0,G41/G10) -> 0.097727273 | H42: =IF(H10=0,0,H41/H10) -> 0.097727273

Sheet Balance Sheet
A1: Balance Sheet
A2: CONFIDENTIAL – Board of Directors, CEO and CFO only. Amounts in USD. Fictional test data. Blue = hardcoded input, black = formula, green = link to another sheet.
A4: USD | B4: 31 Dec 2024 | C4: 31 Dec 2025 | D4: 30 Sep 2026
A5: ASSETS
A6: Cash & equivalents (derived) | B6: =B26-B7-B8-B10 -> 1061000 | C6: =C26-C7-C8-C10 -> 1151000 | D6: =D26-D7-D8-D10 -> 1350750
A7: Accounts receivable | B7: 380000 | C7: 450000 | D7: 520000
A8: Prepaid & other current assets | B8: 40000 | C8: 48000 | D8: 55000
A9: Total current assets | B9: =SUM(B6:B8) -> 1481000 | C9: =SUM(C6:C8) -> 1649000 | D9: =SUM(D6:D8) -> 1925750
A10: Equipment & fixtures (net) | B10: 210000 | C10: 232000 | D10: 235000
A11: TOTAL ASSETS | B11: =B9+B10 -> 1691000 | C11: =C9+C10 -> 1881000 | D11: =D9+D10 -> 2160750
A13: LIABILITIES
A14: Accounts payable | B14: 150000 | C14: 170000 | D14: 190000
A15: Accrued salaries & expenses | B15: 110000 | C15: 125000 | D15: 140000
A16: Income tax payable | B16: 62000 | C16: 70000 | D16: 95000
A17: Current portion of bank loan | B17: 60000 | C17: 60000 | D17: 60000
A18: Total current liabilities | B18: =SUM(B14:B17) -> 382000 | C18: =SUM(C14:C17) -> 425000 | D18: =SUM(D14:D17) -> 485000
A19: Long-term bank loan | B19: 180000 | C19: 120000 | D19: 75000
A20: Total Liabilities | B20: =B18+B19 -> 562000 | C20: =C18+C19 -> 545000 | D20: =D18+D19 -> 560000
A22: EQUITY
A23: Share capital | B23: =Assumptions!$B$11 -> 500000 | C23: =Assumptions!$B$11 -> 500000 | D23: =Assumptions!$B$11 -> 500000
A24: Retained earnings | B24: =Assumptions!$B$10+'Income Statement'!B41-Assumptions!$B$12 -> 629000 | C24: =B24+'Income Statement'!C41-Assumptions!$B$8 -> 836000 | D24: =C24+'Income Statement'!G41-Assumptions!$B$9 -> 1100750
A25: Total Equity | B25: =B23+B24 -> 1129000 | C25: =C23+C24 -> 1336000 | D25: =D23+D24 -> 1600750
A26: TOTAL LIABILITIES & EQUITY | B26: =B20+B25 -> 1691000 | C26: =C20+C25 -> 1881000 | D26: =D20+D25 -> 2160750
A27: Balance check (Assets – L&E, must be 0) | B27: =ROUND(B11-B26,2) -> 0 | C27: =ROUND(C11-C26,2) -> 0 | D27: =ROUND(D11-D26,2) -> 0

Sheet Cash Flow
A1: Cash Flow Statement (indirect method)
A2: CONFIDENTIAL – Board of Directors, CEO and CFO only. Amounts in USD. Fictional test data. Blue = hardcoded input, black = formula, green = link to another sheet.
A4: USD | B4: FY2025 | C4: 2026 YTD (9M)
A5: Net profit | B5: ='Income Statement'!C41 -> 327000 | C5: ='Income Statement'!G41 -> 354750
A6: Add: Depreciation | B6: ='Income Statement'!C32 -> 100000 | C6: ='Income Statement'!G32 -> 79500
A7: (Increase)/decrease in accounts receivable | B7: ='Balance Sheet'!B7-'Balance Sheet'!C7 -> -70000 | C7: ='Balance Sheet'!C7-'Balance Sheet'!D7 -> -70000
A8: (Increase)/decrease in prepaid & other | B8: ='Balance Sheet'!B8-'Balance Sheet'!C8 -> -8000 | C8: ='Balance Sheet'!C8-'Balance Sheet'!D8 -> -7000
A9: Increase/(decrease) in accounts payable | B9: ='Balance Sheet'!C14-'Balance Sheet'!B14 -> 20000 | C9: ='Balance Sheet'!D14-'Balance Sheet'!C14 -> 20000
A10: Increase/(decrease) in accrued expenses | B10: ='Balance Sheet'!C15-'Balance Sheet'!B15 -> 15000 | C10: ='Balance Sheet'!D15-'Balance Sheet'!C15 -> 15000
A11: Increase/(decrease) in income tax payable | B11: ='Balance Sheet'!C16-'Balance Sheet'!B16 -> 8000 | C11: ='Balance Sheet'!D16-'Balance Sheet'!C16 -> 25000
A12: Net cash from operating activities | B12: =SUM(B5:B11) -> 392000 | C12: =SUM(C5:C11) -> 417250
A13: INVESTING ACTIVITIES
A14: Purchase of equipment (net of disposals) | B14: =-('Balance Sheet'!C10-'Balance Sheet'!B10+B6) -> -122000 | C14: =-('Balance Sheet'!D10-'Balance Sheet'!C10+C6) -> -82500
A15: Net cash used in investing activities | B15: =B14 -> -122000 | C15: =C14 -> -82500
A16: FINANCING ACTIVITIES
A17: Bank loan repayments | B17: =('Balance Sheet'!C17+'Balance Sheet'!C19)-('Balance Sheet'!B17+'Balance Sheet'!B19) -> -60000 | C17: =('Balance Sheet'!D17+'Balance Sheet'!D19)-('Balance Sheet'!C17+'Balance Sheet'!C19) -> -45000
A18: Dividends paid | B18: =-Assumptions!$B$8 -> -120000 | C18: =-Assumptions!$B$9 -> -90000
A19: Net cash used in financing activities | B19: =B17+B18 -> -180000 | C19: =C17+C18 -> -135000
A20: Net change in cash | B20: =B12+B15+B19 -> 90000 | C20: =C12+C15+C19 -> 199750
A21: Opening cash | B21: ='Balance Sheet'!B6 -> 1061000 | C21: ='Balance Sheet'!C6 -> 1151000
A22: Closing cash | B22: =B20+B21 -> 1151000 | C22: =C20+C21 -> 1350750
A23: Check vs Balance Sheet (must be 0) | B23: =ROUND(B22-'Balance Sheet'!C6,2) -> 0 | C23: =ROUND(C22-'Balance Sheet'!D6,2) -> 0

Sheet Payroll Reconciliation
A1: Payroll Reconciliation – September 2026
A2: CONFIDENTIAL – Board of Directors, CEO and CFO only. Amounts in USD. Fictional test data. Blue = hardcoded input, black = formula, green = link to another sheet.
A4: Department | B4: Employees | C4: Gross Pay (Sep 2026) | D4: Net Pay (Sep 2026) | E4: Mapped to P&L line
A5: Executive | B5: 1 | C5: 21250 | D5: 15725 | E5: G&A salaries
A6: Finance | B6: 3 | C6: 38316.66 | D6: 30645.16 | E6: G&A salaries
A7: Human Resources | B7: 2 | C7: 17550 | D7: 15247 | E7: G&A salaries
A8: Operations | B8: 2 | C8: 17300 | D8: 14547.17 | E8: G&A salaries
A9: Sales | B9: 3 | C9: 29183.34 | D9: 24603.01 | E9: Sales & Marketing salaries
A10: Marketing | B10: 3 | C10: 24666.66 | D10: 21399.16 | E10: Sales & Marketing salaries
A11: Technology | B11: 6 | C11: 69233.34 | D11: 57119.51 | E11: Delivery team salaries
A12: Total | B12: =SUM(B5:B11) -> 20 | C12: =SUM(C5:C11) -> 217500 | D12: =SUM(D5:D11) -> 179286.01
A13: Per Payroll Register (file 02) – gross | C13: 217500
A14: Difference (must be 0) | C14: =ROUND(C12-C13,2) -> 0
A17: P&L line | C17: Q3 2026 per Income Statement | D17: 3 × Sep 2026 gross | E17: Difference (must be 0)
A18: Delivery team salaries (Technology) | C18: ='Income Statement'!F13 -> 207700.02 | D18: =C11*3 -> 207700.02 | E18: =ROUND(C18-D18,2) -> 0
A19: Sales & Marketing salaries | C19: ='Income Statement'!F21 -> 161550 | D19: =(C9+C10)*3 -> 161550 | E19: =ROUND(C19-D19,2) -> 0
A20: G&A salaries (Exec, Finance, HR, Ops) | C20: ='Income Statement'!F22 -> 283249.98 | D20: =(C5+C6+C7+C8)*3 -> 283249.98 | E20: =ROUND(C20-D20,2) -> 0
A22: Annualised gross payroll (Sep gross × 12) | C22: =C12*12 -> 2610000
A23: Annualised payroll as % of annualised revenue | C23: =C22/'Income Statement'!H10 -> 0.5392562

Sheet Assumptions
A1: Assumptions & Notes
A2: CONFIDENTIAL – Board of Directors, CEO and CFO only. Amounts in USD. Fictional test data. Blue = hardcoded input, black = formula, green = link to another sheet.
A4: Assumption | B4: Value | C4: Notes
A5: Income tax rate | B5: 0.25 | C5: Applied to profit before tax; no tax credit on losses.
A6: Headcount (employees) | B6: 20 | C6: Per Employee Database.
A7: Days in 2026 YTD period (1 Jan–30 Sep) | B7: 273 | C7: Used for DSO.
A8: Dividends paid – FY2025 | B8: 120000 | C8: Declared and paid in cash.
A9: Dividends paid – 2026 YTD | B9: 90000 | C9: Interim dividends paid Jan–Sep 2026.
A10: Retained earnings at 31 Dec 2023 | B10: 600000 | C10: Opening balance.
A11: Share capital (unchanged) | B11: 500000 | C11: No share issues in the period.
A12: Dividends paid – FY2024 | B12: 100000
A15: Notes:
A16: 1. Financial year = calendar year. FY2024 and FY2025 are full-year figures; 2026 shows Q1–Q3 (January–September) and year-to-date.
A17: 2. Salary lines for Q3 2026 equal 3 × the September 2026 gross payroll in the Payroll Register (assumes July and August payroll equal September). Q1/Q2 and prior years are scaled estimates.
A18: 3. Cash is derived so that the balance sheet balances (Total Liabilities & Equity less other assets); reconcile to bank statements in a real close.
A19: 4. All other revenue and expense figures are illustrative inputs created for testing; they are not real company data.
A20: 5. Group health insurance (employer share) is assumed at $150 per employee per month; the employee deduction of $75 is shown on payslips.
