Workbook

Sheet Asset Register
A1: Nexora Technologies Ltd. — Office Asset Register
A2: Accumulated depreciation, net book value, employee name, department and warranty status are formulas. Report date set on the Assumptions sheet (05-Oct-2026).
A4: Asset Tag | B4: Category | C4: Description | D4: Make / Model | E4: Serial No. | F4: Purchase Date | G4: Vendor | H4: Cost (USD) | I4: Useful Life (yrs) | J4: Accum. Depreciation | K4: Net Book Value | L4: Assigned To (Emp ID) | M4: Assignment Type | N4: Employee / Custodian | O4: Department | P4: Location | Q4: Condition | R4: Status | S4: Warranty Expiry | T4: Warranty Status | U4: Last Audit | V4: Audit Status
A5: NX-AST-0001 | B5: Laptop | C5: Dell XPS 15 Laptop | D5: Dell XPS 15 9530 | E5: DXPRV7RTVGT | F5: 44569 | G5: Dell Technologies | H5: 2100 | I5: 4 | J5: =ROUND(MIN(H5,H5/I5*(Assumptions!$B$4-F5)/365.25),2) -> 2100 | K5: =H5-J5 -> 0 | L5: NX-001 | M5: Personal | N5: =IF(L5="","— (unassigned)",INDEX('Employee Lookup'!$B$5:$B$24,MATCH(L5,'Employee Lookup'!$A$5:$A$24,0))) -> Daniel Carter | O5: =IF(L5="","—",INDEX('Employee Lookup'!$C$5:$C$24,MATCH(L5,'Employee Lookup'!$A$5:$A$24,0))) -> Executive | P5: Head Office | Q5: Fair | R5: In Use | S5: 45665 | T5: =IF(S5<Assumptions!$B$4,"Expired",IF(S5-Assumptions!$B$4<=Assumptions!$B$6,"Expiring soon","Valid")) -> Expired | U5: 46006 | V5: =IF(Assumptions!$B$4-U5>Assumptions!$B$7,"Overdue","OK") -> OK
A6: NX-AST-0002 | B6: Monitor | C6: Dell UltraSharp 27" Monitor | D6: Dell U2723QE | E6: CN0X2DLD3ZB | F6: 44569 | G6: Dell Technologies | H6: 320 | I6: 5 | J6: =ROUND(MIN(H6,H6/I6*(Assumptions!$B$4-F6)/365.25),2) -> 303.31 | K6: =H6-J6 -> 16.69 | L6: NX-001 | M6: Personal | N6: =IF(L6="","— (unassigned)",INDEX('Employee Lookup'!$B$5:$B$24,MATCH(L6,'Employee Lookup'!$A$5:$A$24,0))) -> Daniel Carter | O6: =IF(L6="","—",INDEX('Employee Lookup'!$C$5:$C$24,MATCH(L6,'Employee Lookup'!$A$5:$A$24,0))) -> Executive | P6: Head Office | Q6: Fair | R6: In Use | S6: 45665 | T6: =IF(S6<Assumptions!$B$4,"Expired",IF(S6-Assumptions!$B$4<=Assumptions!$B$6,"Expiring soon","Valid")) -> Expired | U6: 46203 | V6: =IF(Assumptions!$B$4-U6>Assumptions!$B$7,"Overdue","OK") -> OK
A7: NX-AST-0003 | B7: Mobile Phone | C7: Apple iPhone 15 (128GB) | D7: Apple iPhone 15 | E7: F2L98YWFATC | F7: 45352 | G7: Carrier Business Store | H7: 999 | I7: 3 | J7: =ROUND(MIN(H7,H7/I7*(Assumptions!$B$4-F7)/365.25),2) -> 864.3 | K7: =H7-J7 -> 134.7 | L7: NX-001 | M7: Personal | N7: =IF(L7="","— (unassigned)",INDEX('Employee Lookup'!$B$5:$B$24,MATCH(L7,'Employee Lookup'!$A$5:$A$24,0))) -> Daniel Carter | O7: =IF(L7="","—",INDEX('Employee Lookup'!$C$5:$C$24,MATCH(L7,'Employee Lookup'!$A$5:$A$24,0))) -> Executive | P7: Head Office | Q7: Good | R7: In Use | S7: 45717 | T7: =IF(S7<Assumptions!$B$4,"Expired",IF(S7-Assumptions!$B$4<=Assumptions!$B$6,"Expiring soon","Valid")) -> Expired | U7: 46203 | V7: =IF(Assumptions!$B$4-U7>Assumptions!$B$7,"Overdue","OK") -> OK
A8: NX-AST-0004 | B8: Furniture | C8: Office Desk and Ergonomic Chair Set | D8: Herman Miller / Custom Desk | E8: HMGJBRQ4TX | F8: 43617 | G8: Office Furnishings Co. | H8: 650 | I8: 8 | J8: =ROUND(MIN(H8,H8/I8*(Assumptions!$B$4-F8)/365.25),2) -> 596.83 | K8: =H8-J8 -> 53.17 | L8: NX-001 | M8: Personal | N8: =IF(L8="","— (unassigned)",INDEX('Employee Lookup'!$B$5:$B$24,MATCH(L8,'Employee Lookup'!$A$5:$A$24,0))) -> Daniel Carter | O8: =IF(L8="","—",INDEX('Employee Lookup'!$C$5:$C$24,MATCH(L8,'Employee Lookup'!$A$5:$A$24,0))) -> Executive | P8: Head Office | Q8: Fair | R8: In Use | S8: 45444 | T8: =IF(S8<Assumptions!$B$4,"Expired",IF(S8-Assumptions!$B$4<=Assumptions!$B$6,"Expiring soon","Valid")) -> Expired | U8: 46203 | V8: =IF(Assumptions!$B$4-U8>Assumptions!$B$7,"Overdue","OK") -> OK
A9: NX-AST-0005 | B9: Laptop | C9: Lenovo ThinkPad T14 Gen 4 | D9: Lenovo ThinkPad T14 Gen 4 | E9: PF3SYRK9940 | F9: 45086 | G9: Lenovo Direct | H9: 1350 | I9: 4 | J9: =ROUND(MIN(H9,H9/I9*(Assumptions!$B$4-F9)/365.25),2) -> 1121.77 | K9: =H9-J9 -> 228.23 | L9: NX-002 | M9: Personal | N9: =IF(L9="","— (unassigned)",INDEX('Employee Lookup'!$B$5:$B$24,MATCH(L9,'Employee Lookup'!$A$5:$A$24,0))) -> Sophia Bennett | O9: =IF(L9="","—",INDEX('Employee Lookup'!$C$5:$C$24,MATCH(L9,'Employee Lookup'!$A$5:$A$24,0))) -> Finance | P9: Head Office | Q9: Fair | R9: In Use | S9: 46182 | T9: =IF(S9<Assumptions!$B$4,"Expired",IF(S9-Assumptions!$B$4<=Assumptions!$B$6,"Expiring soon","Valid")) -> Expired | U9: 46203 | V9: =IF(Assumptions!$B$4-U9>Assumptions!$B$7,"Overdue","OK") -> OK
A10: NX-AST-0006 | B10: Monitor | C10: Dell UltraSharp 27" Monitor | D10: Dell U2723QE | E10: CN0LHKC2P4P | F10: 45086 | G10: Dell Technologies | H10: 320 | I10: 5 | J10: =ROUND(MIN(H10,H10/I10*(Assumptions!$B$4-F10)/365.25),2) -> 212.72 | K10: =H10-J10 -> 107.28 | L10: NX-002 | M10: Personal | N10: =IF(L10="","— (unassigned)",INDEX('Employee Lookup'!$B$5:$B$24,MATCH(L10,'Employee Lookup'!$A$5:$A$24,0))) -> Sophia Bennett | O10: =IF(L10="","—",INDEX('Employee Lookup'!$C$5:$C$24,MATCH(L10,'Employee Lookup'!$A$5:$A$24,0))) -> Finance | P10: Head Office | Q10: Fair | R10: In Use | S10: 46182 | T10: =IF(S10<Assumptions!$B$4,"Expired",IF(S10-Assumptions!$B$4<=Assumptions!$B$6,"Expiring soon","Valid")) -> Expired | U10: 46203 | V10: =IF(Assumptions!$B$4-U10>Assumptions!$B$7,"Overdue","OK") -> OK
A11: NX-AST-0007 | B11: Furniture | C11: Office Desk and Ergonomic Chair Set | D11: Herman Miller / Custom Desk | E11: HM84AH6R9P | F11: 43617 | G11: Office Furnishings Co. | H11: 650 | I11: 8 | J11: =ROUND(MIN(H11,H11/I11*(Assumptions!$B$4-F11)/365.25),2) -> 596.83 | K11: =H11-J11 -> 53.17 | L11: NX-002 | M11: Personal | N11: =IF(L11="","— (unassigned)",INDEX('Employee Lookup'!$B$5:$B$24,MATCH(L11,'Employee Lookup'!$A$5:$A$24,0))) -> Sophia Bennett | O11: =IF(L11="","—",INDEX('Employee Lookup'!$C$5:$C$24,MATCH(L11,'Employee Lookup'!$A$5:$A$24,0))) -> Finance | P11: Head Office | Q11: Fair | R11: In Use | S11: 45444 | T11: =IF(S11<Assumptions!$B$4,"Expired",IF(S11-Assumptions!$B$4<=Assumptions!$B$6,"Expiring soon","Valid")) -> Expired | U11: 46203 | V11: =IF(Assumptions!$B$4-U11>Assumptions!$B$7,"Overdue","OK") -> OK
A12: NX-AST-0008 | B12: Laptop | C12: MacBook Pro 14-inch (M3) | D12: Apple MacBook Pro 14 | E12: FVFCX2KCM81 | F12: 45606 | G12: Apple Business | H12: 2400 | I12: 4 | J12: =ROUND(MIN(H12,H12/I12*(Assumptions!$B$4-F12)/365.25),2) -> 1140.04 | K12: =H12-J12 -> 1259.96 | L12: NX-003 | M12: Personal | N12: =IF(L12="","— (unassigned)",INDEX('Employee Lookup'!$B$5:$B$24,MATCH(L12,'Employee Lookup'!$A$5:$A$24,0))) -> Marcus Reed | O12: =IF(L12="","—",INDEX('Employee Lookup'!$C$5:$C$24,MATCH(L12,'Employee Lookup'!$A$5:$A$24,0))) -> Technology | P12: Head Office | Q12: Good | R12: In Use | S12: 46701 | T12: =IF(S12<Assumptions!$B$4,"Expired",IF(S12-Assumptions!$B$4<=Assumptions!$B$6,"Expiring soon","Valid")) -> Valid | U12: 46203 | V12: =IF(Assumptions!$B$4-U12>Assumptions!$B$7,"Overdue","OK") -> OK
A13: NX-AST-0009 | B13: Monitor | C13: Dell UltraSharp 27" Monitor | D13: Dell U2723QE | E13: CN0EJDC3GVR | F13: 45606 | G13: Dell Technologies | H13: 320 | I13: 5 | J13: =ROUND(MIN(H13,H13/I13*(Assumptions!$B$4-F13)/365.25),2) -> 121.6 | K13: =H13-J13 -> 198.4 | L13: NX-003 | M13: Personal | N13: =IF(L13="","— (unassigned)",INDEX('Employee Lookup'!$B$5:$B$24,MATCH(L13,'Employee Lookup'!$A$5:$A$24,0))) -> Marcus Reed | O13: =IF(L13="","—",INDEX('Employee Lookup'!$C$5:$C$24,MATCH(L13,'Employee Lookup'!$A$5:$A$24,0))) -> Technology | P13: Head Office | Q13: Good | R13: In Use | S13: 46701 | T13: =IF(S13<Assumptions!$B$4,"Expired",IF(S13-Assumptions!$B$4<=Assumptions!$B$6,"Expiring soon","Valid")) -> Valid | U13: 46203 | V13: =IF(Assumptions!$B$4-U13>Assumptions!$B$7,"Overdue","OK") -> OK
A14: NX-AST-0010 | B14: Docking Station | C14: USB-C Docking Station | D14: Dell WD22TB4 | E14: DKG0EXDQHK | F14: 45606 | G14: Dell Technologies | H14: 240 | I14: 5 | J14: =ROUND(MIN(H14,H14/I14*(Assumptions!$B$4-F14)/365.25),2) -> 91.2 | K14: =H14-J14 -> 148.8 | L14: NX-003 | M14: Personal | N14: =IF(L14="","— (unassigned)",INDEX('Employee Lookup'!$B$5:$B$24,MATCH(L14,'Employee Lookup'!$A$5:$A$24,0))) -> Marcus Reed | O14: =IF(L14="","—",INDEX('Employee Lookup'!$C$5:$C$24,MATCH(L14,'Employee Lookup'!$A$5:$A$24,0))) -> Technology | P14: Head Office | Q14: Good | R14: In Use | S14: 46701 | T14: =IF(S14<Assumptions!$B$4,"Expired",IF(S14-Assumptions!$B$4<=Assumptions!$B$6,"Expiring soon","Valid")) -> Valid | U14: 46203 | V14: =IF(Assumptions!$B$4-U14>Assumptions!$B$7,"Overdue","OK") -> OK
A15: NX-AST-0011 | B15: Mobile Phone | C15: Apple iPhone 15 (128GB) | D15: Apple iPhone 15 | E15: F2L93L6HP5X | F15: 45352 | G15: Carrier Business Store | H15: 999 | I15: 3 | J15: =ROUND(MIN(H15,H15/I15*(Assumptions!$B$4-F15)/365.25),2) -> 864.3 | K15: =H15-J15 -> 134.7 | L15: NX-003 | M15: Personal | N15: =IF(L15="","— (unassigned)",INDEX('Employee Lookup'!$B$5:$B$24,MATCH(L15,'Employee Lookup'!$A$5:$A$24,0))) -> Marcus Reed | O15: =IF(L15="","—",INDEX('Employee Lookup'!$C$5:$C$24,MATCH(L15,'Employee Lookup'!$A$5:$A$24,0))) -> Technology | P15: Head Office | Q15: Good | R15: In Use | S15: 45717 | T15: =IF(S15<Assumptions!$B$4,"Expired",IF(S15-Assumptions!$B$4<=Assumptions!$B$6,"Expiring soon","Valid")) -> Expired | U15: 46203 | V15: =IF(Assumptions!$B$4-U15>Assumptions!$B$7,"Overdue","OK") -> OK
A16: NX-AST-0012 | B16: Furniture | C16: Office Desk and Ergonomic Chair Set | D16: Herman Miller / Custom Desk | E16: HMD9HJ2MLC | F16: 43617 | G16: Office Furnishings Co. | H16: 650 | I16: 8 | J16: =ROUND(MIN(H16,H16/I16*(Assumptions!$B$4-F16)/365.25),2) -> 596.83 | K16: =H16-J16 -> 53.17 | L16: NX-003 | M16: Personal | N16: =IF(L16="","— (unassigned)",INDEX('Employee Lookup'!$B$5:$B$24,MATCH(L16,'Employee Lookup'!$A$5:$A$24,0))) -> Marcus Reed | O16: =IF(L16="","—",INDEX('Employee Lookup'!$C$5:$C$24,MATCH(L16,'Employee Lookup'!$A$5:$A$24,0))) -> Technology | P16: Head Office | Q16: Fair | R16: In Use | S16: 45444 | T16: =IF(S16<Assumptions!$B$4,"Expired",IF(S16-Assumptions!$B$4<=Assumptions!$B$6,"Expiring soon","Valid")) -> Expired | U16: 46006 | V16: =IF(Assumptions!$B$4-U16>Assumptions!$B$7,"Overdue","OK") -> OK
... A100: NX-AST-0096 | B100: Monitor | C100: Dell UltraSharp 27" Monitor (spare) | D100: Dell U2723QE | E100: CN0CRV6BDGH | F100: 45432 | G100: Dell Technologies | H100: 320 | I100: 5 | J100: =ROUND(MIN(H100,H100/I100*(Assumptions!$B$4-F100)/365.25),2) -> 152.09 | K100: =H100-J100 -> 167.91 | L100: NX-019 | M100: Spare stock | N100: =IF(L100="","— (unassigned)",INDEX('Employee Lookup'!$B$5:$B$24,MATCH(L100,'Employee Lookup'!$A$5:$A$24,0))) -> Jack Stewart | O100: =IF(L100="","—",INDEX('Employee Lookup'!$C$5:$C$24,MATCH(L100,'Employee Lookup'!$A$5:$A$24,0))) -> Technology | P100: Head Office - IT Store | Q100: Good | R100: In Stock | S100: 46527 | T100: =IF(S100<Assumptions!$B$4,"Expired",IF(S100-Assumptions!$B$4<=Assumptions!$B$6,"Expiring soon","Valid")) -> Valid | U100: 46203 | V100: =IF(Assumptions!$B$4-U100>Assumptions!$B$7,"Overdue","OK") -> OK
A101: NX-AST-0097 | B101: Laptop | C101: Dell Latitude 5420 (returned by former employee, left Mar 2026) | D101: Dell Latitude 5420 | E101: DLTJ0WHGKF1 | F101: 44228 | G101: Dell Technologies | H101: 1200 | I101: 4 | J101: =ROUND(MIN(H101,H101/I101*(Assumptions!$B$4-F101)/365.25),2) -> 1200 | K101: =H101-J101 -> 0 | M101: Spare stock | N101: =IF(L101="","— (unassigned)",INDEX('Employee Lookup'!$B$5:$B$24,MATCH(L101,'Employee Lookup'!$A$5:$A$24,0))) -> — (unassigned) | O101: =IF(L101="","—",INDEX('Employee Lookup'!$C$5:$C$24,MATCH(L101,'Employee Lookup'!$A$5:$A$24,0))) -> — | P101: Head Office - IT Store | Q101: Poor | R101: Retired | S101: 45323 | T101: =IF(S101<Assumptions!$B$4,"Expired",IF(S101-Assumptions!$B$4<=Assumptions!$B$6,"Expiring soon","Valid")) -> Expired | U101: 46114 | V101: =IF(Assumptions!$B$4-U101>Assumptions!$B$7,"Overdue","OK") -> OK
A103: TOTAL | B103: =COUNTA(A5:A101)&" assets" -> 97 assets | H103: =SUM(H5:H101) -> 105493 | J103: =SUM(J5:J101) -> 80370.52 | K103: =SUM(K5:K101) -> 25122.48

Sheet By Employee
A1: Assets Assigned by Employee
A2: Counts personal assignments only (shared equipment is held by custodians and counted separately).
A4: Employee ID | B4: Full Name | C4: Department | D4: Work Location | E4: Personal Assets | F4: Shared Items Held (custodian) | G4: Total Cost (personal) | H4: Net Book Value (personal) | I4: Under Repair
A5: NX-001 | B5: Daniel Carter | C5: Executive | D5: Head Office | E5: =COUNTIFS('Asset Register'!$L$5:$L$101,$A5,'Asset Register'!$M$5:$M$101,"Personal") -> 4 | F5: =COUNTIFS('Asset Register'!$L$5:$L$101,$A5,'Asset Register'!$M$5:$M$101,"Shared (custodian)") -> 0 | G5: =SUMIFS('Asset Register'!$H$5:$H$101,'Asset Register'!$L$5:$L$101,$A5,'Asset Register'!$M$5:$M$101,"Personal") -> 4069 | H5: =SUMIFS('Asset Register'!$K$5:$K$101,'Asset Register'!$L$5:$L$101,$A5,'Asset Register'!$M$5:$M$101,"Personal") -> 204.56 | I5: =COUNTIFS('Asset Register'!$L$5:$L$101,$A5,'Asset Register'!$R$5:$R$101,"Under Repair") -> 0
A6: NX-002 | B6: Sophia Bennett | C6: Finance | D6: Head Office | E6: =COUNTIFS('Asset Register'!$L$5:$L$101,$A6,'Asset Register'!$M$5:$M$101,"Personal") -> 3 | F6: =COUNTIFS('Asset Register'!$L$5:$L$101,$A6,'Asset Register'!$M$5:$M$101,"Shared (custodian)") -> 0 | G6: =SUMIFS('Asset Register'!$H$5:$H$101,'Asset Register'!$L$5:$L$101,$A6,'Asset Register'!$M$5:$M$101,"Personal") -> 2320 | H6: =SUMIFS('Asset Register'!$K$5:$K$101,'Asset Register'!$L$5:$L$101,$A6,'Asset Register'!$M$5:$M$101,"Personal") -> 388.68 | I6: =COUNTIFS('Asset Register'!$L$5:$L$101,$A6,'Asset Register'!$R$5:$R$101,"Under Repair") -> 0
A7: NX-003 | B7: Marcus Reed | C7: Technology | D7: Head Office | E7: =COUNTIFS('Asset Register'!$L$5:$L$101,$A7,'Asset Register'!$M$5:$M$101,"Personal") -> 5 | F7: =COUNTIFS('Asset Register'!$L$5:$L$101,$A7,'Asset Register'!$M$5:$M$101,"Shared (custodian)") -> 1 | G7: =SUMIFS('Asset Register'!$H$5:$H$101,'Asset Register'!$L$5:$L$101,$A7,'Asset Register'!$M$5:$M$101,"Personal") -> 4609 | H7: =SUMIFS('Asset Register'!$K$5:$K$101,'Asset Register'!$L$5:$L$101,$A7,'Asset Register'!$M$5:$M$101,"Personal") -> 1795.03 | I7: =COUNTIFS('Asset Register'!$L$5:$L$101,$A7,'Asset Register'!$R$5:$R$101,"Under Repair") -> 0
A8: NX-004 | B8: Olivia Hughes | C8: Human Resources | D8: Head Office | E8: =COUNTIFS('Asset Register'!$L$5:$L$101,$A8,'Asset Register'!$M$5:$M$101,"Personal") -> 4 | F8: =COUNTIFS('Asset Register'!$L$5:$L$101,$A8,'Asset Register'!$M$5:$M$101,"Shared (custodian)") -> 0 | G8: =SUMIFS('Asset Register'!$H$5:$H$101,'Asset Register'!$L$5:$L$101,$A8,'Asset Register'!$M$5:$M$101,"Personal") -> 3319 | H8: =SUMIFS('Asset Register'!$K$5:$K$101,'Asset Register'!$L$5:$L$101,$A8,'Asset Register'!$M$5:$M$101,"Personal") -> 220.86 | I8: =COUNTIFS('Asset Register'!$L$5:$L$101,$A8,'Asset Register'!$R$5:$R$101,"Under Repair") -> 0
A9: NX-005 | B9: Ethan Brooks | C9: Technology | D9: Head Office | E9: =COUNTIFS('Asset Register'!$L$5:$L$101,$A9,'Asset Register'!$M$5:$M$101,"Personal") -> 5 | F9: =COUNTIFS('Asset Register'!$L$5:$L$101,$A9,'Asset Register'!$M$5:$M$101,"Shared (custodian)") -> 0 | G9: =SUMIFS('Asset Register'!$H$5:$H$101,'Asset Register'!$L$5:$L$101,$A9,'Asset Register'!$M$5:$M$101,"Personal") -> 4960 | H9: =SUMIFS('Asset Register'!$K$5:$K$101,'Asset Register'!$L$5:$L$101,$A9,'Asset Register'!$M$5:$M$101,"Personal") -> 1814.09 | I9: =COUNTIFS('Asset Register'!$L$5:$L$101,$A9,'Asset Register'!$R$5:$R$101,"Under Repair") -> 1
A10: NX-006 | B10: Isabella Foster | C10: Technology | D10: Head Office | E10: =COUNTIFS('Asset Register'!$L$5:$L$101,$A10,'Asset Register'!$M$5:$M$101,"Personal") -> 4 | F10: =COUNTIFS('Asset Register'!$L$5:$L$101,$A10,'Asset Register'!$M$5:$M$101,"Shared (custodian)") -> 0 | G10: =SUMIFS('Asset Register'!$H$5:$H$101,'Asset Register'!$L$5:$L$101,$A10,'Asset Register'!$M$5:$M$101,"Personal") -> 3610 | H10: =SUMIFS('Asset Register'!$K$5:$K$101,'Asset Register'!$L$5:$L$101,$A10,'Asset Register'!$M$5:$M$101,"Personal") -> 1146.49 | I10: =COUNTIFS('Asset Register'!$L$5:$L$101,$A10,'Asset Register'!$R$5:$R$101,"Under Repair") -> 0
A11: NX-007 | B11: Liam Sanders | C11: Technology | D11: Remote | E11: =COUNTIFS('Asset Register'!$L$5:$L$101,$A11,'Asset Register'!$M$5:$M$101,"Personal") -> 5 | F11: =COUNTIFS('Asset Register'!$L$5:$L$101,$A11,'Asset Register'!$M$5:$M$101,"Shared (custodian)") -> 0 | G11: =SUMIFS('Asset Register'!$H$5:$H$101,'Asset Register'!$L$5:$L$101,$A11,'Asset Register'!$M$5:$M$101,"Personal") -> 3440 | H11: =SUMIFS('Asset Register'!$K$5:$K$101,'Asset Register'!$L$5:$L$101,$A11,'Asset Register'!$M$5:$M$101,"Personal") -> 228.03 | I11: =COUNTIFS('Asset Register'!$L$5:$L$101,$A11,'Asset Register'!$R$5:$R$101,"Under Repair") -> 0
A12: NX-008 | B12: Ava Mitchell | C12: Technology | D12: Head Office | E12: =COUNTIFS('Asset Register'!$L$5:$L$101,$A12,'Asset Register'!$M$5:$M$101,"Personal") -> 4 | F12: =COUNTIFS('Asset Register'!$L$5:$L$101,$A12,'Asset Register'!$M$5:$M$101,"Shared (custodian)") -> 0 | G12: =SUMIFS('Asset Register'!$H$5:$H$101,'Asset Register'!$L$5:$L$101,$A12,'Asset Register'!$M$5:$M$101,"Personal") -> 3610 | H12: =SUMIFS('Asset Register'!$K$5:$K$101,'Asset Register'!$L$5:$L$101,$A12,'Asset Register'!$M$5:$M$101,"Personal") -> 1158.79 | I12: =COUNTIFS('Asset Register'!$L$5:$L$101,$A12,'Asset Register'!$R$5:$R$101,"Under Repair") -> 0
A13: NX-009 | B13: Noah Parker | C13: Sales | D13: Head Office | E13: =COUNTIFS('Asset Register'!$L$5:$L$101,$A13,'Asset Register'!$M$5:$M$101,"Personal") -> 4 | F13: =COUNTIFS('Asset Register'!$L$5:$L$101,$A13,'Asset Register'!$M$5:$M$101,"Shared (custodian)") -> 0 | G13: =SUMIFS('Asset Register'!$H$5:$H$101,'Asset Register'!$L$5:$L$101,$A13,'Asset Register'!$M$5:$M$101,"Personal") -> 3369 | H13: =SUMIFS('Asset Register'!$K$5:$K$101,'Asset Register'!$L$5:$L$101,$A13,'Asset Register'!$M$5:$M$101,"Personal") -> 919.49 | I13: =COUNTIFS('Asset Register'!$L$5:$L$101,$A13,'Asset Register'!$R$5:$R$101,"Under Repair") -> 0
A14: NX-010 | B14: Emma Collins | C14: Sales | D14: Branch Office | E14: =COUNTIFS('Asset Register'!$L$5:$L$101,$A14,'Asset Register'!$M$5:$M$101,"Personal") -> 3 | F14: =COUNTIFS('Asset Register'!$L$5:$L$101,$A14,'Asset Register'!$M$5:$M$101,"Shared (custodian)") -> 0 | G14: =SUMIFS('Asset Register'!$H$5:$H$101,'Asset Register'!$L$5:$L$101,$A14,'Asset Register'!$M$5:$M$101,"Personal") -> 3049 | H14: =SUMIFS('Asset Register'!$K$5:$K$101,'Asset Register'!$L$5:$L$101,$A14,'Asset Register'!$M$5:$M$101,"Personal") -> 230.95 | I14: =COUNTIFS('Asset Register'!$L$5:$L$101,$A14,'Asset Register'!$R$5:$R$101,"Under Repair") -> 0
A15: NX-011 | B15: James Ward | C15: Sales | D15: Branch Office | E15: =COUNTIFS('Asset Register'!$L$5:$L$101,$A15,'Asset Register'!$M$5:$M$101,"Personal") -> 3 | F15: =COUNTIFS('Asset Register'!$L$5:$L$101,$A15,'Asset Register'!$M$5:$M$101,"Shared (custodian)") -> 0 | G15: =SUMIFS('Asset Register'!$H$5:$H$101,'Asset Register'!$L$5:$L$101,$A15,'Asset Register'!$M$5:$M$101,"Personal") -> 3049 | H15: =SUMIFS('Asset Register'!$K$5:$K$101,'Asset Register'!$L$5:$L$101,$A15,'Asset Register'!$M$5:$M$101,"Personal") -> 507.4 | I15: =COUNTIFS('Asset Register'!$L$5:$L$101,$A15,'Asset Register'!$R$5:$R$101,"Under Repair") -> 0
A16: NX-012 | B16: Mia Turner | C16: Marketing | D16: Head Office | E16: =COUNTIFS('Asset Register'!$L$5:$L$101,$A16,'Asset Register'!$M$5:$M$101,"Personal") -> 3 | F16: =COUNTIFS('Asset Register'!$L$5:$L$101,$A16,'Asset Register'!$M$5:$M$101,"Shared (custodian)") -> 0 | G16: =SUMIFS('Asset Register'!$H$5:$H$101,'Asset Register'!$L$5:$L$101,$A16,'Asset Register'!$M$5:$M$101,"Personal") -> 2320 | H16: =SUMIFS('Asset Register'!$K$5:$K$101,'Asset Register'!$L$5:$L$101,$A16,'Asset Register'!$M$5:$M$101,"Personal") -> 869.05 | I16: =COUNTIFS('Asset Register'!$L$5:$L$101,$A16,'Asset Register'!$R$5:$R$101,"Under Repair") -> 0
... A24: NX-020 | B24: Ella Morgan | C24: Marketing | D24: Remote | E24: =COUNTIFS('Asset Register'!$L$5:$L$101,$A24,'Asset Register'!$M$5:$M$101,"Personal") -> 4 | F24: =COUNTIFS('Asset Register'!$L$5:$L$101,$A24,'Asset Register'!$M$5:$M$101,"Shared (custodian)") -> 0 | G24: =SUMIFS('Asset Register'!$H$5:$H$101,'Asset Register'!$L$5:$L$101,$A24,'Asset Register'!$M$5:$M$101,"Personal") -> 2150 | H24: =SUMIFS('Asset Register'!$K$5:$K$101,'Asset Register'!$L$5:$L$101,$A24,'Asset Register'!$M$5:$M$101,"Personal") -> 820.69 | I24: =COUNTIFS('Asset Register'!$L$5:$L$101,$A24,'Asset Register'!$R$5:$R$101,"Under Repair") -> 0
A25: TOTAL | E25: =SUM(E5:E24) -> 75 | F25: =SUM(F5:F24) -> 18 | G25: =SUM(G5:G24) -> 62233 | H25: =SUM(H5:H24) -> 13610.67 | I25: =SUM(I5:I24) -> 1

Sheet By Category
A1: Assets by Category
A2: All figures are formulas from the Asset Register.
A4: Category | B4: Number of Assets | C4: In Use | D4: In Stock | E4: Under Repair | F4: Retired | G4: Total Cost | H4: Accum. Depreciation | I4: Net Book Value
A5: AV Equipment | B5: =COUNTIF('Asset Register'!$B$5:$B$101,$A5) -> 3 | C5: =COUNTIFS('Asset Register'!$B$5:$B$101,$A5,'Asset Register'!$R$5:$R$101,"In Use") -> 3 | D5: =COUNTIFS('Asset Register'!$B$5:$B$101,$A5,'Asset Register'!$R$5:$R$101,"In Stock") -> 0 | E5: =COUNTIFS('Asset Register'!$B$5:$B$101,$A5,'Asset Register'!$R$5:$R$101,"Under Repair") -> 0 | F5: =COUNTIFS('Asset Register'!$B$5:$B$101,$A5,'Asset Register'!$R$5:$R$101,"Retired") -> 0 | G5: =SUMIF('Asset Register'!$B$5:$B$101,$A5,'Asset Register'!$H$5:$H$101) -> 5750 | H5: =SUMIF('Asset Register'!$B$5:$B$101,$A5,'Asset Register'!$J$5:$J$101) -> 3875.05 | I5: =SUMIF('Asset Register'!$B$5:$B$101,$A5,'Asset Register'!$K$5:$K$101) -> 1874.95
A6: Appliance & Facilities | B6: =COUNTIF('Asset Register'!$B$5:$B$101,$A6) -> 2 | C6: =COUNTIFS('Asset Register'!$B$5:$B$101,$A6,'Asset Register'!$R$5:$R$101,"In Use") -> 2 | D6: =COUNTIFS('Asset Register'!$B$5:$B$101,$A6,'Asset Register'!$R$5:$R$101,"In Stock") -> 0 | E6: =COUNTIFS('Asset Register'!$B$5:$B$101,$A6,'Asset Register'!$R$5:$R$101,"Under Repair") -> 0 | F6: =COUNTIFS('Asset Register'!$B$5:$B$101,$A6,'Asset Register'!$R$5:$R$101,"Retired") -> 0 | G6: =SUMIF('Asset Register'!$B$5:$B$101,$A6,'Asset Register'!$H$5:$H$101) -> 3700 | H6: =SUMIF('Asset Register'!$B$5:$B$101,$A6,'Asset Register'!$J$5:$J$101) -> 2429.62 | I6: =SUMIF('Asset Register'!$B$5:$B$101,$A6,'Asset Register'!$K$5:$K$101) -> 1270.38
A7: Docking Station | B7: =COUNTIF('Asset Register'!$B$5:$B$101,$A7) -> 6 | C7: =COUNTIFS('Asset Register'!$B$5:$B$101,$A7,'Asset Register'!$R$5:$R$101,"In Use") -> 6 | D7: =COUNTIFS('Asset Register'!$B$5:$B$101,$A7,'Asset Register'!$R$5:$R$101,"In Stock") -> 0 | E7: =COUNTIFS('Asset Register'!$B$5:$B$101,$A7,'Asset Register'!$R$5:$R$101,"Under Repair") -> 0 | F7: =COUNTIFS('Asset Register'!$B$5:$B$101,$A7,'Asset Register'!$R$5:$R$101,"Retired") -> 0 | G7: =SUMIF('Asset Register'!$B$5:$B$101,$A7,'Asset Register'!$H$5:$H$101) -> 1440 | H7: =SUMIF('Asset Register'!$B$5:$B$101,$A7,'Asset Register'!$J$5:$J$101) -> 863.68 | I7: =SUMIF('Asset Register'!$B$5:$B$101,$A7,'Asset Register'!$K$5:$K$101) -> 576.32
A8: Furniture | B8: =COUNTIF('Asset Register'!$B$5:$B$101,$A8) -> 22 | C8: =COUNTIFS('Asset Register'!$B$5:$B$101,$A8,'Asset Register'!$R$5:$R$101,"In Use") -> 22 | D8: =COUNTIFS('Asset Register'!$B$5:$B$101,$A8,'Asset Register'!$R$5:$R$101,"In Stock") -> 0 | E8: =COUNTIFS('Asset Register'!$B$5:$B$101,$A8,'Asset Register'!$R$5:$R$101,"Under Repair") -> 0 | F8: =COUNTIFS('Asset Register'!$B$5:$B$101,$A8,'Asset Register'!$R$5:$R$101,"Retired") -> 0 | G8: =SUMIF('Asset Register'!$B$5:$B$101,$A8,'Asset Register'!$H$5:$H$101) -> 18250 | H8: =SUMIF('Asset Register'!$B$5:$B$101,$A8,'Asset Register'!$J$5:$J$101) -> 13958.56 | I8: =SUMIF('Asset Register'!$B$5:$B$101,$A8,'Asset Register'!$K$5:$K$101) -> 4291.44
A9: Headset | B9: =COUNTIF('Asset Register'!$B$5:$B$101,$A9) -> 3 | C9: =COUNTIFS('Asset Register'!$B$5:$B$101,$A9,'Asset Register'!$R$5:$R$101,"In Use") -> 3 | D9: =COUNTIFS('Asset Register'!$B$5:$B$101,$A9,'Asset Register'!$R$5:$R$101,"In Stock") -> 0 | E9: =COUNTIFS('Asset Register'!$B$5:$B$101,$A9,'Asset Register'!$R$5:$R$101,"Under Repair") -> 0 | F9: =COUNTIFS('Asset Register'!$B$5:$B$101,$A9,'Asset Register'!$R$5:$R$101,"Retired") -> 0 | G9: =SUMIF('Asset Register'!$B$5:$B$101,$A9,'Asset Register'!$H$5:$H$101) -> 540 | H9: =SUMIF('Asset Register'!$B$5:$B$101,$A9,'Asset Register'!$J$5:$J$101) -> 519.84 | I9: =SUMIF('Asset Register'!$B$5:$B$101,$A9,'Asset Register'!$K$5:$K$101) -> 20.16
A10: Laptop | B10: =COUNTIF('Asset Register'!$B$5:$B$101,$A10) -> 24 | C10: =COUNTIFS('Asset Register'!$B$5:$B$101,$A10,'Asset Register'!$R$5:$R$101,"In Use") -> 20 | D10: =COUNTIFS('Asset Register'!$B$5:$B$101,$A10,'Asset Register'!$R$5:$R$101,"In Stock") -> 2 | E10: =COUNTIFS('Asset Register'!$B$5:$B$101,$A10,'Asset Register'!$R$5:$R$101,"Under Repair") -> 1 | F10: =COUNTIFS('Asset Register'!$B$5:$B$101,$A10,'Asset Register'!$R$5:$R$101,"Retired") -> 1 | G10: =SUMIF('Asset Register'!$B$5:$B$101,$A10,'Asset Register'!$H$5:$H$101) -> 39450 | H10: =SUMIF('Asset Register'!$B$5:$B$101,$A10,'Asset Register'!$J$5:$J$101) -> 29870.34 | I10: =SUMIF('Asset Register'!$B$5:$B$101,$A10,'Asset Register'!$K$5:$K$101) -> 9579.66
A11: Mobile Phone | B11: =COUNTIF('Asset Register'!$B$5:$B$101,$A11) -> 7 | C11: =COUNTIFS('Asset Register'!$B$5:$B$101,$A11,'Asset Register'!$R$5:$R$101,"In Use") -> 7 | D11: =COUNTIFS('Asset Register'!$B$5:$B$101,$A11,'Asset Register'!$R$5:$R$101,"In Stock") -> 0 | E11: =COUNTIFS('Asset Register'!$B$5:$B$101,$A11,'Asset Register'!$R$5:$R$101,"Under Repair") -> 0 | F11: =COUNTIFS('Asset Register'!$B$5:$B$101,$A11,'Asset Register'!$R$5:$R$101,"Retired") -> 0 | G11: =SUMIF('Asset Register'!$B$5:$B$101,$A11,'Asset Register'!$H$5:$H$101) -> 6993 | H11: =SUMIF('Asset Register'!$B$5:$B$101,$A11,'Asset Register'!$J$5:$J$101) -> 6050.1 | I11: =SUMIF('Asset Register'!$B$5:$B$101,$A11,'Asset Register'!$K$5:$K$101) -> 942.9
A12: Monitor | B12: =COUNTIF('Asset Register'!$B$5:$B$101,$A12) -> 19 | C12: =COUNTIFS('Asset Register'!$B$5:$B$101,$A12,'Asset Register'!$R$5:$R$101,"In Use") -> 18 | D12: =COUNTIFS('Asset Register'!$B$5:$B$101,$A12,'Asset Register'!$R$5:$R$101,"In Stock") -> 1 | E12: =COUNTIFS('Asset Register'!$B$5:$B$101,$A12,'Asset Register'!$R$5:$R$101,"Under Repair") -> 0 | F12: =COUNTIFS('Asset Register'!$B$5:$B$101,$A12,'Asset Register'!$R$5:$R$101,"Retired") -> 0 | G12: =SUMIF('Asset Register'!$B$5:$B$101,$A12,'Asset Register'!$H$5:$H$101) -> 6080 | H12: =SUMIF('Asset Register'!$B$5:$B$101,$A12,'Asset Register'!$J$5:$J$101) -> 4045.86 | I12: =SUMIF('Asset Register'!$B$5:$B$101,$A12,'Asset Register'!$K$5:$K$101) -> 2034.14
A13: Network & Server | B13: =COUNTIF('Asset Register'!$B$5:$B$101,$A13) -> 7 | C13: =COUNTIFS('Asset Register'!$B$5:$B$101,$A13,'Asset Register'!$R$5:$R$101,"In Use") -> 7 | D13: =COUNTIFS('Asset Register'!$B$5:$B$101,$A13,'Asset Register'!$R$5:$R$101,"In Stock") -> 0 | E13: =COUNTIFS('Asset Register'!$B$5:$B$101,$A13,'Asset Register'!$R$5:$R$101,"Under Repair") -> 0 | F13: =COUNTIFS('Asset Register'!$B$5:$B$101,$A13,'Asset Register'!$R$5:$R$101,"Retired") -> 0 | G13: =SUMIF('Asset Register'!$B$5:$B$101,$A13,'Asset Register'!$H$5:$H$101) -> 17530 | H13: =SUMIF('Asset Register'!$B$5:$B$101,$A13,'Asset Register'!$J$5:$J$101) -> 14968.28 | I13: =SUMIF('Asset Register'!$B$5:$B$101,$A13,'Asset Register'!$K$5:$K$101) -> 2561.72
A14: Printer | B14: =COUNTIF('Asset Register'!$B$5:$B$101,$A14) -> 2 | C14: =COUNTIFS('Asset Register'!$B$5:$B$101,$A14,'Asset Register'!$R$5:$R$101,"In Use") -> 2 | D14: =COUNTIFS('Asset Register'!$B$5:$B$101,$A14,'Asset Register'!$R$5:$R$101,"In Stock") -> 0 | E14: =COUNTIFS('Asset Register'!$B$5:$B$101,$A14,'Asset Register'!$R$5:$R$101,"Under Repair") -> 0 | F14: =COUNTIFS('Asset Register'!$B$5:$B$101,$A14,'Asset Register'!$R$5:$R$101,"Retired") -> 0 | G14: =SUMIF('Asset Register'!$B$5:$B$101,$A14,'Asset Register'!$H$5:$H$101) -> 1160 | H14: =SUMIF('Asset Register'!$B$5:$B$101,$A14,'Asset Register'!$J$5:$J$101) -> 820.46 | I14: =SUMIF('Asset Register'!$B$5:$B$101,$A14,'Asset Register'!$K$5:$K$101) -> 339.54
A15: Security | B15: =COUNTIF('Asset Register'!$B$5:$B$101,$A15) -> 2 | C15: =COUNTIFS('Asset Register'!$B$5:$B$101,$A15,'Asset Register'!$R$5:$R$101,"In Use") -> 2 | D15: =COUNTIFS('Asset Register'!$B$5:$B$101,$A15,'Asset Register'!$R$5:$R$101,"In Stock") -> 0 | E15: =COUNTIFS('Asset Register'!$B$5:$B$101,$A15,'Asset Register'!$R$5:$R$101,"Under Repair") -> 0 | F15: =COUNTIFS('Asset Register'!$B$5:$B$101,$A15,'Asset Register'!$R$5:$R$101,"Retired") -> 0 | G15: =SUMIF('Asset Register'!$B$5:$B$101,$A15,'Asset Register'!$H$5:$H$101) -> 4600 | H15: =SUMIF('Asset Register'!$B$5:$B$101,$A15,'Asset Register'!$J$5:$J$101) -> 2968.73 | I15: =SUMIF('Asset Register'!$B$5:$B$101,$A15,'Asset Register'!$K$5:$K$101) -> 1631.27
A16: TOTAL | B16: =SUM(B5:B15) -> 97 | C16: =SUM(C5:C15) -> 92 | D16: =SUM(D5:D15) -> 3 | E16: =SUM(E5:E15) -> 1 | F16: =SUM(F5:F15) -> 1 | G16: =SUM(G5:G15) -> 105493 | H16: =SUM(H5:H15) -> 80370.52 | I16: =SUM(I5:I15) -> 25122.48

Sheet Reconciliation
A1: Reconciliation to Balance Sheet
A2: The register itemises IT, office equipment and furniture. The balance sheet also holds leasehold improvements, fixtures and other assets not itemised here.
A4: Item | B4: USD
A5: Register – total cost | B5: =SUM('Asset Register'!$H$5:$H$101) -> 105493
A6: Register – accumulated depreciation | B6: =SUM('Asset Register'!$J$5:$J$101) -> 80370.52
A7: Register – net book value | B7: =SUM('Asset Register'!$K$5:$K$101) -> 25122.48
A8: Equipment & fixtures (net) per Balance Sheet, 30-Sep-2026 | B8: =Assumptions!B8 -> 235000
A9: Difference (non-itemised fixtures, leasehold improvements, etc.) | B9: =B8-B7 -> 209877.52
A10: Register NBV as % of balance sheet | B10: =B7/B8 -> 0.10690417

Sheet Employee Lookup
A1: Employee Lookup (from Employee Database)
A2: Reference list used for name/department lookups.
A4: Employee ID | B4: Full Name | C4: Department | D4: Designation | E4: Work Location
A5: NX-001 | B5: Daniel Carter | C5: Executive | D5: Chief Executive Officer | E5: Head Office
A6: NX-002 | B6: Sophia Bennett | C6: Finance | D6: Chief Financial Officer | E6: Head Office
A7: NX-003 | B7: Marcus Reed | C7: Technology | D7: Chief Technology Officer | E7: Head Office
A8: NX-004 | B8: Olivia Hughes | C8: Human Resources | D8: HR Manager | E8: Head Office
A9: NX-005 | B9: Ethan Brooks | C9: Technology | D9: Senior Software Engineer | E9: Head Office
A10: NX-006 | B10: Isabella Foster | C10: Technology | D10: Software Engineer | E10: Head Office
A11: NX-007 | B11: Liam Sanders | C11: Technology | D11: Software Engineer | E11: Remote
A12: NX-008 | B12: Ava Mitchell | C12: Technology | D12: QA Engineer | E12: Head Office
A13: NX-009 | B13: Noah Parker | C13: Sales | D13: Sales Manager | E13: Head Office
A14: NX-010 | B14: Emma Collins | C14: Sales | D14: Sales Executive | E14: Branch Office
A15: NX-011 | B15: James Ward | C15: Sales | D15: Sales Executive | E15: Branch Office
... A24: NX-020 | B24: Ella Morgan | C24: Marketing | D24: Content Writer | E24: Remote

Sheet Assumptions
A1: Assumptions & Notes
A2: Blue = input. Change the report date and all depreciation and warranty flags update.
A3: Item | B3: Value | C3: Notes
A4: Report date | B4: 46300 | C4: Depreciation and warranty status are calculated as at this date.
A5: Depreciation method | B5: Straight-line | C5: Cost / useful life, nil residual value, pro-rated by days from purchase date; stops when fully depreciated.
A6: Warranty 'expiring soon' window (days) | B6: 90 | C6: Warranty within this many days of expiry is flagged.
A7: Audit overdue after (days) | B7: 365 | C7: Physical audit older than this is flagged as overdue.
A8: Equipment & fixtures (net) per Balance Sheet 30-Sep-2026 | B8: 235000 | C8: From the Company Financial Report (file 07).
A11: Notes:
A12: 1. Every employee has a company laptop (policy). Remote staff also have a headset and ergonomic chair under the home-office setup allowance. Employees at the Head Office and Branch Office have a desk set.
A13: 2. Shared equipment is assigned to a custodian (an employee responsible for it). Personal assignments are counted per employee on the By Employee sheet.
A14: 3. NX-005 (Ethan Brooks) has a laptop under repair and a loaner laptop. A retired laptop was returned by a former employee.
A15: 4. Master employee details are copied from the Employee Database (file 01). All asset data is fictional.
